--- Bytecode Analysis for: Malayo.pyc ---
--- Python Runtime Version: 3.13.9 ---

   0            RESUME                   0

   3            LOAD_CONST               0 (0)
                LOAD_CONST               1 (None)
                IMPORT_NAME              0 (z3)
                STORE_NAME               0 (z3)

   4            LOAD_CONST               0 (0)
                LOAD_CONST               1 (None)
                IMPORT_NAME              1 (random)
                STORE_NAME               1 (random)

   5            LOAD_CONST               0 (0)
                LOAD_CONST               1 (None)
                IMPORT_NAME              2 (hashlib)
                STORE_NAME               2 (hashlib)

   6            LOAD_CONST               0 (0)
                LOAD_CONST               1 (None)
                IMPORT_NAME              3 (base64)
                STORE_NAME               3 (base64)

   7            LOAD_CONST               0 (0)
                LOAD_CONST               1 (None)
                IMPORT_NAME              4 (string)
                STORE_NAME               4 (string)

   8            LOAD_CONST               0 (0)
                LOAD_CONST               1 (None)
                IMPORT_NAME              5 (time)
                STORE_NAME               5 (time)

   9            LOAD_CONST               0 (0)
                LOAD_CONST               1 (None)
                IMPORT_NAME              6 (sys)
                STORE_NAME               6 (sys)

  10            LOAD_CONST               0 (0)
                LOAD_CONST               2 (('permutations', 'combinations'))
                IMPORT_NAME              7 (itertools)
                IMPORT_FROM              8 (permutations)
                STORE_NAME               8 (permutations)
                IMPORT_FROM              9 (combinations)
                STORE_NAME               9 (combinations)
                POP_TOP

  11            LOAD_CONST               0 (0)
                LOAD_CONST               3 (('reduce',))
                IMPORT_NAME             10 (functools)
                IMPORT_FROM             11 (reduce)
                STORE_NAME              11 (reduce)
                POP_TOP

  12            LOAD_CONST               0 (0)
                LOAD_CONST               4 (('defaultdict',))
                IMPORT_NAME             12 (collections)
                IMPORT_FROM             13 (defaultdict)
                STORE_NAME              13 (defaultdict)
                POP_TOP

  13            LOAD_CONST               0 (0)
                LOAD_CONST               5 (('AES',))
                IMPORT_NAME             14 (Crypto.Cipher)
                IMPORT_FROM             15 (AES)
                STORE_NAME              15 (AES)
                POP_TOP

  14            LOAD_CONST               0 (0)
                LOAD_CONST               6 (('pad', 'unpad'))
                IMPORT_NAME             16 (Crypto.Util.Padding)
                IMPORT_FROM             17 (pad)
                STORE_NAME              17 (pad)
                IMPORT_FROM             18 (unpad)
                STORE_NAME              18 (unpad)
                POP_TOP

  15            LOAD_CONST               0 (0)
                LOAD_CONST               1 (None)
                IMPORT_NAME             19 (os)
                STORE_NAME              19 (os)

  19            LOAD_CONST               7 ('Lorem ipsum dolor sit amet consectetur adipiscing elit')
                LOAD_CONST               8 (100)
                BINARY_OP                5 (*)

  20            LOAD_CONST               9 ('The quick brown fox jumps over the lazy dogThe quick brown fox jumps over the lazy dogThe quick brown fox jumps over the lazy dogThe quick brown fox jumps over the lazy dogThe quick brown fox jumps over the lazy dogThe quick brown fox jumps over the lazy dogThe quick brown fox jumps over the lazy dogThe quick brown fox jumps over the lazy dogThe quick brown fox jumps over the lazy dogThe quick brown fox jumps over the lazy dogThe quick brown fox jumps over the lazy dogThe quick brown fox jumps over the lazy dogThe quick brown fox jumps over the lazy dogThe quick brown fox jumps over the lazy dogThe quick brown fox jumps over the lazy dogThe quick brown fox jumps over the lazy dogThe quick brown fox jumps over the lazy dogThe quick brown fox jumps over the lazy dogThe quick brown fox jumps over the lazy dogThe quick brown fox jumps over the lazy dogThe quick brown fox jumps over the lazy dogThe quick brown fox jumps over the lazy dogThe quick brown fox jumps over the lazy dogThe quick brown fox jumps over the lazy dogThe quick brown fox jumps over the lazy dogThe quick brown fox jumps over the lazy dogThe quick brown fox jumps over the lazy dogThe quick brown fox jumps over the lazy dogThe quick brown fox jumps over the lazy dogThe quick brown fox jumps over the lazy dogThe quick brown fox jumps over the lazy dogThe quick brown fox jumps over the lazy dogThe quick brown fox jumps over the lazy dogThe quick brown fox jumps over the lazy dogThe quick brown fox jumps over the lazy dogThe quick brown fox jumps over the lazy dogThe quick brown fox jumps over the lazy dogThe quick brown fox jumps over the lazy dogThe quick brown fox jumps over the lazy dogThe quick brown fox jumps over the lazy dogThe quick brown fox jumps over the lazy dogThe quick brown fox jumps over the lazy dogThe quick brown fox jumps over the lazy dogThe quick brown fox jumps over the lazy dogThe quick brown fox jumps over the lazy dogThe quick brown fox jumps over the lazy dogThe quick brown fox jumps over the lazy dogThe quick brown fox jumps over the lazy dogThe quick brown fox jumps over the lazy dogThe quick brown fox jumps over the lazy dogThe quick brown fox jumps over the lazy dogThe quick brown fox jumps over the lazy dogThe quick brown fox jumps over the lazy dogThe quick brown fox jumps over the lazy dogThe quick brown fox jumps over the lazy dogThe quick brown fox jumps over the lazy dogThe quick brown fox jumps over the lazy dogThe quick brown fox jumps over the lazy dogThe quick brown fox jumps over the lazy dogThe quick brown fox jumps over the lazy dogThe quick brown fox jumps over the lazy dogThe quick brown fox jumps over the lazy dogThe quick brown fox jumps over the lazy dogThe quick brown fox jumps over the lazy dogThe quick brown fox jumps over the lazy dogThe quick brown fox jumps over the lazy dogThe quick brown fox jumps over the lazy dogThe quick brown fox jumps over the lazy dogThe quick brown fox jumps over the lazy dogThe quick brown fox jumps over the lazy dogThe quick brown fox jumps over the lazy dogThe quick brown fox jumps over the lazy dogThe quick brown fox jumps over the lazy dogThe quick brown fox jumps over the lazy dogThe quick brown fox jumps over the lazy dog')

  21            LOAD_CONST              10 ('Pack my box with five dozen liquor jugsPack my box with five dozen liquor jugsPack my box with five dozen liquor jugsPack my box with five dozen liquor jugsPack my box with five dozen liquor jugsPack my box with five dozen liquor jugsPack my box with five dozen liquor jugsPack my box with five dozen liquor jugsPack my box with five dozen liquor jugsPack my box with five dozen liquor jugsPack my box with five dozen liquor jugsPack my box with five dozen liquor jugsPack my box with five dozen liquor jugsPack my box with five dozen liquor jugsPack my box with five dozen liquor jugsPack my box with five dozen liquor jugsPack my box with five dozen liquor jugsPack my box with five dozen liquor jugsPack my box with five dozen liquor jugsPack my box with five dozen liquor jugsPack my box with five dozen liquor jugsPack my box with five dozen liquor jugsPack my box with five dozen liquor jugsPack my box with five dozen liquor jugsPack my box with five dozen liquor jugsPack my box with five dozen liquor jugsPack my box with five dozen liquor jugsPack my box with five dozen liquor jugsPack my box with five dozen liquor jugsPack my box with five dozen liquor jugsPack my box with five dozen liquor jugsPack my box with five dozen liquor jugsPack my box with five dozen liquor jugsPack my box with five dozen liquor jugsPack my box with five dozen liquor jugsPack my box with five dozen liquor jugsPack my box with five dozen liquor jugsPack my box with five dozen liquor jugsPack my box with five dozen liquor jugsPack my box with five dozen liquor jugsPack my box with five dozen liquor jugsPack my box with five dozen liquor jugsPack my box with five dozen liquor jugsPack my box with five dozen liquor jugsPack my box with five dozen liquor jugsPack my box with five dozen liquor jugsPack my box with five dozen liquor jugsPack my box with five dozen liquor jugsPack my box with five dozen liquor jugsPack my box with five dozen liquor jugsPack my box with five dozen liquor jugsPack my box with five dozen liquor jugsPack my box with five dozen liquor jugsPack my box with five dozen liquor jugsPack my box with five dozen liquor jugsPack my box with five dozen liquor jugsPack my box with five dozen liquor jugsPack my box with five dozen liquor jugsPack my box with five dozen liquor jugsPack my box with five dozen liquor jugs')

  22            LOAD_CONST              11 ('Sphinx of black quartz judge my vowSphinx of black quartz judge my vowSphinx of black quartz judge my vowSphinx of black quartz judge my vowSphinx of black quartz judge my vowSphinx of black quartz judge my vowSphinx of black quartz judge my vowSphinx of black quartz judge my vowSphinx of black quartz judge my vowSphinx of black quartz judge my vowSphinx of black quartz judge my vowSphinx of black quartz judge my vowSphinx of black quartz judge my vowSphinx of black quartz judge my vowSphinx of black quartz judge my vowSphinx of black quartz judge my vowSphinx of black quartz judge my vowSphinx of black quartz judge my vowSphinx of black quartz judge my vowSphinx of black quartz judge my vowSphinx of black quartz judge my vowSphinx of black quartz judge my vowSphinx of black quartz judge my vowSphinx of black quartz judge my vowSphinx of black quartz judge my vowSphinx of black quartz judge my vowSphinx of black quartz judge my vowSphinx of black quartz judge my vowSphinx of black quartz judge my vowSphinx of black quartz judge my vowSphinx of black quartz judge my vowSphinx of black quartz judge my vowSphinx of black quartz judge my vowSphinx of black quartz judge my vowSphinx of black quartz judge my vowSphinx of black quartz judge my vowSphinx of black quartz judge my vowSphinx of black quartz judge my vowSphinx of black quartz judge my vowSphinx of black quartz judge my vowSphinx of black quartz judge my vowSphinx of black quartz judge my vowSphinx of black quartz judge my vowSphinx of black quartz judge my vowSphinx of black quartz judge my vowSphinx of black quartz judge my vowSphinx of black quartz judge my vowSphinx of black quartz judge my vowSphinx of black quartz judge my vowSphinx of black quartz judge my vowSphinx of black quartz judge my vowSphinx of black quartz judge my vowSphinx of black quartz judge my vowSphinx of black quartz judge my vowSphinx of black quartz judge my vowSphinx of black quartz judge my vowSphinx of black quartz judge my vowSphinx of black quartz judge my vowSphinx of black quartz judge my vowSphinx of black quartz judge my vowSphinx of black quartz judge my vowSphinx of black quartz judge my vowSphinx of black quartz judge my vowSphinx of black quartz judge my vowSphinx of black quartz judge my vowSphinx of black quartz judge my vowSphinx of black quartz judge my vowSphinx of black quartz judge my vowSphinx of black quartz judge my vowSphinx of black quartz judge my vowSphinx of black quartz judge my vowSphinx of black quartz judge my vowSphinx of black quartz judge my vowSphinx of black quartz judge my vowSphinx of black quartz judge my vowSphinx of black quartz judge my vowSphinx of black quartz judge my vowSphinx of black quartz judge my vowSphinx of black quartz judge my vowSphinx of black quartz judge my vow')

  23            LOAD_CONST              12 ('Waltz bad nymph for quick jigs vexWaltz bad nymph for quick jigs vexWaltz bad nymph for quick jigs vexWaltz bad nymph for quick jigs vexWaltz bad nymph for quick jigs vexWaltz bad nymph for quick jigs vexWaltz bad nymph for quick jigs vexWaltz bad nymph for quick jigs vexWaltz bad nymph for quick jigs vexWaltz bad nymph for quick jigs vexWaltz bad nymph for quick jigs vexWaltz bad nymph for quick jigs vexWaltz bad nymph for quick jigs vexWaltz bad nymph for quick jigs vexWaltz bad nymph for quick jigs vexWaltz bad nymph for quick jigs vexWaltz bad nymph for quick jigs vexWaltz bad nymph for quick jigs vexWaltz bad nymph for quick jigs vexWaltz bad nymph for quick jigs vexWaltz bad nymph for quick jigs vexWaltz bad nymph for quick jigs vexWaltz bad nymph for quick jigs vexWaltz bad nymph for quick jigs vexWaltz bad nymph for quick jigs vexWaltz bad nymph for quick jigs vexWaltz bad nymph for quick jigs vexWaltz bad nymph for quick jigs vexWaltz bad nymph for quick jigs vexWaltz bad nymph for quick jigs vexWaltz bad nymph for quick jigs vexWaltz bad nymph for quick jigs vexWaltz bad nymph for quick jigs vexWaltz bad nymph for quick jigs vexWaltz bad nymph for quick jigs vexWaltz bad nymph for quick jigs vexWaltz bad nymph for quick jigs vexWaltz bad nymph for quick jigs vexWaltz bad nymph for quick jigs vexWaltz bad nymph for quick jigs vexWaltz bad nymph for quick jigs vexWaltz bad nymph for quick jigs vexWaltz bad nymph for quick jigs vexWaltz bad nymph for quick jigs vexWaltz bad nymph for quick jigs vexWaltz bad nymph for quick jigs vexWaltz bad nymph for quick jigs vexWaltz bad nymph for quick jigs vexWaltz bad nymph for quick jigs vexWaltz bad nymph for quick jigs vexWaltz bad nymph for quick jigs vexWaltz bad nymph for quick jigs vexWaltz bad nymph for quick jigs vexWaltz bad nymph for quick jigs vexWaltz bad nymph for quick jigs vexWaltz bad nymph for quick jigs vexWaltz bad nymph for quick jigs vexWaltz bad nymph for quick jigs vexWaltz bad nymph for quick jigs vexWaltz bad nymph for quick jigs vexWaltz bad nymph for quick jigs vexWaltz bad nymph for quick jigs vexWaltz bad nymph for quick jigs vexWaltz bad nymph for quick jigs vexWaltz bad nymph for quick jigs vexWaltz bad nymph for quick jigs vexWaltz bad nymph for quick jigs vexWaltz bad nymph for quick jigs vexWaltz bad nymph for quick jigs vexWaltz bad nymph for quick jigs vexWaltz bad nymph for quick jigs vexWaltz bad nymph for quick jigs vexWaltz bad nymph for quick jigs vexWaltz bad nymph for quick jigs vexWaltz bad nymph for quick jigs vexWaltz bad nymph for quick jigs vexWaltz bad nymph for quick jigs vexWaltz bad nymph for quick jigs vexWaltz bad nymph for quick jigs vexWaltz bad nymph for quick jigs vexWaltz bad nymph for quick jigs vexWaltz bad nymph for quick jigs vexWaltz bad nymph for quick jigs vexWaltz bad nymph for quick jigs vexWaltz bad nymph for quick jigs vexWaltz bad nymph for quick jigs vexWaltz bad nymph for quick jigs vexWaltz bad nymph for quick jigs vexWaltz bad nymph for quick jigs vexWaltz bad nymph for quick jigs vex')

  24            LOAD_CONST              13 ('Glib jocks quiz nymph to vex dwarfGlib jocks quiz nymph to vex dwarfGlib jocks quiz nymph to vex dwarfGlib jocks quiz nymph to vex dwarfGlib jocks quiz nymph to vex dwarfGlib jocks quiz nymph to vex dwarfGlib jocks quiz nymph to vex dwarfGlib jocks quiz nymph to vex dwarfGlib jocks quiz nymph to vex dwarfGlib jocks quiz nymph to vex dwarfGlib jocks quiz nymph to vex dwarfGlib jocks quiz nymph to vex dwarfGlib jocks quiz nymph to vex dwarfGlib jocks quiz nymph to vex dwarfGlib jocks quiz nymph to vex dwarfGlib jocks quiz nymph to vex dwarfGlib jocks quiz nymph to vex dwarfGlib jocks quiz nymph to vex dwarfGlib jocks quiz nymph to vex dwarfGlib jocks quiz nymph to vex dwarfGlib jocks quiz nymph to vex dwarfGlib jocks quiz nymph to vex dwarfGlib jocks quiz nymph to vex dwarfGlib jocks quiz nymph to vex dwarfGlib jocks quiz nymph to vex dwarfGlib jocks quiz nymph to vex dwarfGlib jocks quiz nymph to vex dwarfGlib jocks quiz nymph to vex dwarfGlib jocks quiz nymph to vex dwarfGlib jocks quiz nymph to vex dwarfGlib jocks quiz nymph to vex dwarfGlib jocks quiz nymph to vex dwarfGlib jocks quiz nymph to vex dwarfGlib jocks quiz nymph to vex dwarfGlib jocks quiz nymph to vex dwarfGlib jocks quiz nymph to vex dwarfGlib jocks quiz nymph to vex dwarfGlib jocks quiz nymph to vex dwarfGlib jocks quiz nymph to vex dwarfGlib jocks quiz nymph to vex dwarfGlib jocks quiz nymph to vex dwarfGlib jocks quiz nymph to vex dwarfGlib jocks quiz nymph to vex dwarfGlib jocks quiz nymph to vex dwarfGlib jocks quiz nymph to vex dwarfGlib jocks quiz nymph to vex dwarfGlib jocks quiz nymph to vex dwarfGlib jocks quiz nymph to vex dwarfGlib jocks quiz nymph to vex dwarfGlib jocks quiz nymph to vex dwarfGlib jocks quiz nymph to vex dwarfGlib jocks quiz nymph to vex dwarfGlib jocks quiz nymph to vex dwarfGlib jocks quiz nymph to vex dwarfGlib jocks quiz nymph to vex dwarfGlib jocks quiz nymph to vex dwarfGlib jocks quiz nymph to vex dwarfGlib jocks quiz nymph to vex dwarfGlib jocks quiz nymph to vex dwarfGlib jocks quiz nymph to vex dwarfGlib jocks quiz nymph to vex dwarfGlib jocks quiz nymph to vex dwarfGlib jocks quiz nymph to vex dwarfGlib jocks quiz nymph to vex dwarfGlib jocks quiz nymph to vex dwarfGlib jocks quiz nymph to vex dwarfGlib jocks quiz nymph to vex dwarfGlib jocks quiz nymph to vex dwarfGlib jocks quiz nymph to vex dwarfGlib jocks quiz nymph to vex dwarfGlib jocks quiz nymph to vex dwarfGlib jocks quiz nymph to vex dwarfGlib jocks quiz nymph to vex dwarfGlib jocks quiz nymph to vex dwarfGlib jocks quiz nymph to vex dwarfGlib jocks quiz nymph to vex dwarfGlib jocks quiz nymph to vex dwarfGlib jocks quiz nymph to vex dwarfGlib jocks quiz nymph to vex dwarfGlib jocks quiz nymph to vex dwarfGlib jocks quiz nymph to vex dwarfGlib jocks quiz nymph to vex dwarfGlib jocks quiz nymph to vex dwarfGlib jocks quiz nymph to vex dwarfGlib jocks quiz nymph to vex dwarf')

  25            LOAD_CONST              14 ('abcdefghijklmnopqrstuvwxyzabcdefghijklmnopqrstuvwxyzabcdefghijklmnopqrstuvwxyzabcdefghijklmnopqrstuvwxyzabcdefghijklmnopqrstuvwxyzabcdefghijklmnopqrstuvwxyzabcdefghijklmnopqrstuvwxyzabcdefghijklmnopqrstuvwxyzabcdefghijklmnopqrstuvwxyzabcdefghijklmnopqrstuvwxyzabcdefghijklmnopqrstuvwxyzabcdefghijklmnopqrstuvwxyzabcdefghijklmnopqrstuvwxyzabcdefghijklmnopqrstuvwxyzabcdefghijklmnopqrstuvwxyzabcdefghijklmnopqrstuvwxyzabcdefghijklmnopqrstuvwxyzabcdefghijklmnopqrstuvwxyzabcdefghijklmnopqrstuvwxyzabcdefghijklmnopqrstuvwxyzabcdefghijklmnopqrstuvwxyzabcdefghijklmnopqrstuvwxyzabcdefghijklmnopqrstuvwxyzabcdefghijklmnopqrstuvwxyzabcdefghijklmnopqrstuvwxyzabcdefghijklmnopqrstuvwxyzabcdefghijklmnopqrstuvwxyzabcdefghijklmnopqrstuvwxyzabcdefghijklmnopqrstuvwxyzabcdefghijklmnopqrstuvwxyzabcdefghijklmnopqrstuvwxyzabcdefghijklmnopqrstuvwxyzabcdefghijklmnopqrstuvwxyzabcdefghijklmnopqrstuvwxyzabcdefghijklmnopqrstuvwxyzabcdefghijklmnopqrstuvwxyzabcdefghijklmnopqrstuvwxyzabcdefghijklmnopqrstuvwxyzabcdefghijklmnopqrstuvwxyzabcdefghijklmnopqrstuvwxyzabcdefghijklmnopqrstuvwxyzabcdefghijklmnopqrstuvwxyzabcdefghijklmnopqrstuvwxyzabcdefghijklmnopqrstuvwxyzabcdefghijklmnopqrstuvwxyzabcdefghijklmnopqrstuvwxyzabcdefghijklmnopqrstuvwxyzabcdefghijklmnopqrstuvwxyzabcdefghijklmnopqrstuvwxyzabcdefghijklmnopqrstuvwxyz')

  26            LOAD_CONST              15 ('ABCDEFGHIJKLMNOPQRSTUVWXYZABCDEFGHIJKLMNOPQRSTUVWXYZABCDEFGHIJKLMNOPQRSTUVWXYZABCDEFGHIJKLMNOPQRSTUVWXYZABCDEFGHIJKLMNOPQRSTUVWXYZABCDEFGHIJKLMNOPQRSTUVWXYZABCDEFGHIJKLMNOPQRSTUVWXYZABCDEFGHIJKLMNOPQRSTUVWXYZABCDEFGHIJKLMNOPQRSTUVWXYZABCDEFGHIJKLMNOPQRSTUVWXYZABCDEFGHIJKLMNOPQRSTUVWXYZABCDEFGHIJKLMNOPQRSTUVWXYZABCDEFGHIJKLMNOPQRSTUVWXYZABCDEFGHIJKLMNOPQRSTUVWXYZABCDEFGHIJKLMNOPQRSTUVWXYZABCDEFGHIJKLMNOPQRSTUVWXYZABCDEFGHIJKLMNOPQRSTUVWXYZABCDEFGHIJKLMNOPQRSTUVWXYZABCDEFGHIJKLMNOPQRSTUVWXYZABCDEFGHIJKLMNOPQRSTUVWXYZABCDEFGHIJKLMNOPQRSTUVWXYZABCDEFGHIJKLMNOPQRSTUVWXYZABCDEFGHIJKLMNOPQRSTUVWXYZABCDEFGHIJKLMNOPQRSTUVWXYZABCDEFGHIJKLMNOPQRSTUVWXYZABCDEFGHIJKLMNOPQRSTUVWXYZABCDEFGHIJKLMNOPQRSTUVWXYZABCDEFGHIJKLMNOPQRSTUVWXYZABCDEFGHIJKLMNOPQRSTUVWXYZABCDEFGHIJKLMNOPQRSTUVWXYZABCDEFGHIJKLMNOPQRSTUVWXYZABCDEFGHIJKLMNOPQRSTUVWXYZABCDEFGHIJKLMNOPQRSTUVWXYZABCDEFGHIJKLMNOPQRSTUVWXYZABCDEFGHIJKLMNOPQRSTUVWXYZABCDEFGHIJKLMNOPQRSTUVWXYZABCDEFGHIJKLMNOPQRSTUVWXYZABCDEFGHIJKLMNOPQRSTUVWXYZABCDEFGHIJKLMNOPQRSTUVWXYZABCDEFGHIJKLMNOPQRSTUVWXYZABCDEFGHIJKLMNOPQRSTUVWXYZABCDEFGHIJKLMNOPQRSTUVWXYZABCDEFGHIJKLMNOPQRSTUVWXYZABCDEFGHIJKLMNOPQRSTUVWXYZABCDEFGHIJKLMNOPQRSTUVWXYZABCDEFGHIJKLMNOPQRSTUVWXYZABCDEFGHIJKLMNOPQRSTUVWXYZABCDEFGHIJKLMNOPQRSTUVWXYZABCDEFGHIJKLMNOPQRSTUVWXYZABCDEFGHIJKLMNOPQRSTUVWXYZ')

  27            LOAD_CONST              16 ('0123456789012345678901234567890123456789012345678901234567890123456789012345678901234567890123456789012345678901234567890123456789012345678901234567890123456789012345678901234567890123456789012345678901234567890123456789012345678901234567890123456789012345678901234567890123456789012345678901234567890123456789012345678901234567890123456789012345678901234567890123456789012345678901234567890123456789012345678901234567890123456789012345678901234567890123456789012345678901234567890123456789012345678901234567890123456789012345678901234567890123456789012345678901234567890123456789012345678901234567890123456789012345678901234567890123456789012345678901234567890123456789012345678901234567890123456789012345678901234567890123456789012345678901234567890123456789012345678901234567890123456789012345678901234567890123456789012345678901234567890123456789012345678901234567890123456789012345678901234567890123456789012345678901234567890123456789012345678901234567890123456789012345678901234567890123456789')

  28            LOAD_CONST              17 ('!@#$%^&*()_+-=[]{}|;:,.<>?!@#$%^&*()_+-=[]{}|;:,.<>?!@#$%^&*()_+-=[]{}|;:,.<>?!@#$%^&*()_+-=[]{}|;:,.<>?!@#$%^&*()_+-=[]{}|;:,.<>?!@#$%^&*()_+-=[]{}|;:,.<>?!@#$%^&*()_+-=[]{}|;:,.<>?!@#$%^&*()_+-=[]{}|;:,.<>?!@#$%^&*()_+-=[]{}|;:,.<>?!@#$%^&*()_+-=[]{}|;:,.<>?!@#$%^&*()_+-=[]{}|;:,.<>?!@#$%^&*()_+-=[]{}|;:,.<>?!@#$%^&*()_+-=[]{}|;:,.<>?!@#$%^&*()_+-=[]{}|;:,.<>?!@#$%^&*()_+-=[]{}|;:,.<>?!@#$%^&*()_+-=[]{}|;:,.<>?!@#$%^&*()_+-=[]{}|;:,.<>?!@#$%^&*()_+-=[]{}|;:,.<>?!@#$%^&*()_+-=[]{}|;:,.<>?!@#$%^&*()_+-=[]{}|;:,.<>?!@#$%^&*()_+-=[]{}|;:,.<>?!@#$%^&*()_+-=[]{}|;:,.<>?!@#$%^&*()_+-=[]{}|;:,.<>?!@#$%^&*()_+-=[]{}|;:,.<>?!@#$%^&*()_+-=[]{}|;:,.<>?')

  17            BUILD_LIST              10

  29            LOAD_CONST              18 (20)

  17            BINARY_OP                5 (*)
                STORE_NAME              20 (STRINGS)

  31            LOAD_NAME               21 (list)
                PUSH_NULL
                LOAD_NAME               22 (range)
                PUSH_NULL
                LOAD_CONST              19 (10000)
                CALL                     1
                CALL                     1
                LOAD_NAME               22 (range)
                PUSH_NULL
                LOAD_CONST              20 (1000)
                CALL                     1
                GET_ITER
                LOAD_FAST_AND_CLEAR      0 (i)
                SWAP                     2
        L1:     BUILD_LIST               0
                SWAP                     2
                GET_ITER
        L2:     FOR_ITER                 7 (to L3)
                STORE_FAST_LOAD_FAST     0 (i, i)
                LOAD_CONST              21 (2)
                BINARY_OP                8 (**)
                LIST_APPEND              2
                JUMP_BACKWARD            9 (to L2)
        L3:     END_FOR
                POP_TOP
        L4:     SWAP                     2
                STORE_FAST               0 (i)
                BINARY_OP                0 (+)
                LOAD_NAME               22 (range)
                PUSH_NULL
                LOAD_CONST              22 (500)
                CALL                     1
                GET_ITER
                LOAD_FAST_AND_CLEAR      0 (i)
                SWAP                     2
        L5:     BUILD_LIST               0
                SWAP                     2
                GET_ITER
        L6:     FOR_ITER                 7 (to L7)
                STORE_FAST_LOAD_FAST     0 (i, i)
                LOAD_CONST              23 (3)
                BINARY_OP                8 (**)
                LIST_APPEND              2
                JUMP_BACKWARD            9 (to L6)
        L7:     END_FOR
                POP_TOP
        L8:     SWAP                     2
                STORE_FAST               0 (i)
                BINARY_OP                0 (+)
                LOAD_NAME               22 (range)
                PUSH_NULL
                LOAD_CONST              24 (30)
                CALL                     1
                GET_ITER
                LOAD_FAST_AND_CLEAR      0 (i)
                SWAP                     2
        L9:     BUILD_LIST               0
                SWAP                     2
                GET_ITER
       L10:     FOR_ITER                 8 (to L11)
                STORE_FAST               0 (i)
                LOAD_CONST              21 (2)
                LOAD_FAST                0 (i)
                BINARY_OP                8 (**)
                LIST_APPEND              2
                JUMP_BACKWARD           10 (to L10)
       L11:     END_FOR
                POP_TOP
       L12:     SWAP                     2
                STORE_FAST               0 (i)
                BINARY_OP                0 (+)
                STORE_NAME              23 (NUMBERS)

  33            LOAD_NAME               22 (range)
                PUSH_NULL
                LOAD_CONST              25 (5000)
                CALL                     1
                GET_ITER
                LOAD_FAST_AND_CLEAR      0 (i)
                SWAP                     2
       L13:     BUILD_MAP                0
                SWAP                     2
                GET_ITER
       L14:     FOR_ITER                15 (to L15)
                STORE_FAST               0 (i)
                LOAD_NAME               24 (str)
                PUSH_NULL
                LOAD_FAST                0 (i)
                CALL                     1
                LOAD_FAST                0 (i)
                LOAD_CONST              21 (2)
                BINARY_OP                5 (*)
                MAP_ADD                  2
                JUMP_BACKWARD           17 (to L14)
       L15:     END_FOR
                POP_TOP
       L16:     SWAP                     2
                STORE_FAST               0 (i)
                STORE_NAME              25 (Xx)

  34            LOAD_NAME               22 (range)
                PUSH_NULL
                LOAD_CONST              26 (26)
                CALL                     1
                GET_ITER
                LOAD_FAST_AND_CLEAR      0 (i)
                SWAP                     2
       L17:     BUILD_MAP                0
                SWAP                     2
                GET_ITER
       L18:     FOR_ITER                15 (to L19)
                STORE_FAST               0 (i)
                LOAD_NAME               26 (chr)
                PUSH_NULL
                LOAD_CONST              27 (65)
                LOAD_FAST                0 (i)
                BINARY_OP                0 (+)
                CALL                     1
                LOAD_FAST                0 (i)
                MAP_ADD                  2
                JUMP_BACKWARD           17 (to L18)
       L19:     END_FOR
                POP_TOP
       L20:     SWAP                     2
                STORE_FAST               0 (i)
                STORE_NAME              27 (xX)

  35            LOAD_NAME               22 (range)
                PUSH_NULL
                LOAD_CONST              28 (2000)
                CALL                     1
                GET_ITER
                LOAD_FAST_AND_CLEAR      0 (i)
                SWAP                     2
       L21:     BUILD_MAP                0
                SWAP                     2
                GET_ITER
       L22:     FOR_ITER                15 (to L23)
                STORE_FAST               0 (i)
                LOAD_CONST              29 ('key_')
                LOAD_FAST                0 (i)
                FORMAT_SIMPLE
                BUILD_STRING             2
                LOAD_CONST              30 ('value_')
                LOAD_FAST                0 (i)
                FORMAT_SIMPLE
                BUILD_STRING             2
                LOAD_CONST              31 (10)
                BINARY_OP                5 (*)
                MAP_ADD                  2
                JUMP_BACKWARD           17 (to L22)
       L23:     END_FOR
                POP_TOP
       L24:     SWAP                     2
                STORE_FAST               0 (i)
                STORE_NAME              28 (XX)

  36            LOAD_NAME               22 (range)
                PUSH_NULL
                LOAD_CONST              20 (1000)
                CALL                     1
                GET_ITER
                LOAD_FAST_AND_CLEAR      0 (i)
                SWAP                     2
       L25:     BUILD_MAP                0
                SWAP                     2
                GET_ITER
       L26:     FOR_ITER                55 (to L27)
                STORE_FAST               0 (i)
                LOAD_NAME                2 (hashlib)
                LOAD_ATTR               59 (md5 + NULL|self)
                LOAD_NAME               24 (str)
                PUSH_NULL
                LOAD_FAST                0 (i)
                CALL                     1
                LOAD_ATTR               61 (encode + NULL|self)
                CALL                     0
                CALL                     1
                LOAD_ATTR               63 (hexdigest + NULL|self)
                CALL                     0
                LOAD_FAST                0 (i)
                MAP_ADD                  2
                JUMP_BACKWARD           57 (to L26)
       L27:     END_FOR
                POP_TOP
       L28:     SWAP                     2
                STORE_FAST               0 (i)
                STORE_NAME              32 (XXx)

  39            LOAD_NAME               22 (range)
                PUSH_NULL
                LOAD_CONST              32 (50)
                CALL                     1
                GET_ITER

  38            LOAD_FAST_AND_CLEAR      1 (_)
                SWAP                     2
       L29:     BUILD_LIST               0
                SWAP                     2

  39            GET_ITER
       L30:     FOR_ITER                44 (to L35)
                STORE_FAST               1 (_)
                LOAD_NAME               22 (range)
                PUSH_NULL
                LOAD_CONST              22 (500)
                CALL                     1
                GET_ITER
                LOAD_FAST_AND_CLEAR      1 (_)
                SWAP                     2
       L31:     BUILD_LIST               0
                SWAP                     2
                GET_ITER
       L32:     FOR_ITER                21 (to L33)
                STORE_FAST               1 (_)
                LOAD_NAME                1 (random)
                LOAD_ATTR               67 (randint + NULL|self)
                LOAD_CONST               0 (0)
                LOAD_CONST              20 (1000)
                CALL                     2
                LIST_APPEND              2
                JUMP_BACKWARD           23 (to L32)
       L33:     END_FOR
                POP_TOP
       L34:     SWAP                     2
                STORE_FAST               1 (_)
                LIST_APPEND              2
                JUMP_BACKWARD           46 (to L30)
       L35:     END_FOR
                POP_TOP

  38   L36:     SWAP                     2
                STORE_FAST               1 (_)
                STORE_NAME              34 (RND1)

  42            LOAD_CONST              33 (<code object hash_function_1 at 0x000002E07A775160, file "./OPz.py", line 42>)
                MAKE_FUNCTION
                STORE_NAME              35 (hash_function_1)

  53            LOAD_CONST              34 (<code object hash_function_2 at 0x000002E07A4D23F0, file "./OPz.py", line 53>)
                MAKE_FUNCTION
                STORE_NAME              36 (hash_function_2)

  57            LOAD_CONST              35 (<code object string_manipulator at 0x000002E07A501D40, file "./OPz.py", line 57>)
                MAKE_FUNCTION
                STORE_NAME              37 (string_manipulator)

  66            LOAD_CONST              36 (<code object operations at 0x000002E07A547280, file "./OPz.py", line 66>)
                MAKE_FUNCTION
                STORE_NAME              38 (operations)

  75            LOAD_CONST              61 ((100,))
                LOAD_CONST              37 (<code object CONSTRAINTSS at 0x000002E07A867D40, file "./OPz.py", line 75>)
                MAKE_FUNCTION
                SET_FUNCTION_ATTRIBUTE   1 (defaults)
                STORE_NAME              39 (CONSTRAINTSS)

  90            LOAD_CONST              38 (<code object CALCSS at 0x000002E07A8991A0, file "./OPz.py", line 90>)
                MAKE_FUNCTION
                STORE_NAME              40 (CALCSS)

 124            LOAD_NAME               22 (range)
                PUSH_NULL
                LOAD_CONST              28 (2000)
                CALL                     1
                GET_ITER
                LOAD_FAST_AND_CLEAR      0 (i)
                SWAP                     2
       L37:     BUILD_LIST               0
                SWAP                     2
                GET_ITER
       L38:     FOR_ITER                17 (to L39)
                STORE_FAST_LOAD_FAST     0 (i, i)
                LOAD_FAST                0 (i)
                LOAD_CONST              21 (2)
                BINARY_OP                5 (*)
                LOAD_FAST                0 (i)
                LOAD_CONST              23 (3)
                BINARY_OP                5 (*)
                LOAD_FAST                0 (i)
                LOAD_CONST              39 (4)
                BINARY_OP                5 (*)
                BUILD_TUPLE              4
                LIST_APPEND              2
                JUMP_BACKWARD           19 (to L38)
       L39:     END_FOR
                POP_TOP
       L40:     SWAP                     2
                STORE_FAST               0 (i)
                STORE_NAME              41 (TUPLES)

 125            LOAD_NAME               22 (range)
                PUSH_NULL
                LOAD_CONST               0 (0)
                LOAD_CONST              20 (1000)
                LOAD_CONST              32 (50)
                CALL                     3
                GET_ITER
                LOAD_FAST_AND_CLEAR      0 (i)
                SWAP                     2
       L41:     BUILD_LIST               0
                SWAP                     2
                GET_ITER
       L42:     FOR_ITER                20 (to L43)
                STORE_FAST               0 (i)
                LOAD_NAME               42 (set)
                PUSH_NULL
                LOAD_NAME               22 (range)
                PUSH_NULL
                LOAD_FAST_LOAD_FAST      0 (i, i)
                LOAD_CONST               8 (100)
                BINARY_OP                0 (+)
                CALL                     2
                CALL                     1
                LIST_APPEND              2
                JUMP_BACKWARD           22 (to L42)
       L43:     END_FOR
                POP_TOP
       L44:     SWAP                     2
                STORE_FAST               0 (i)
                STORE_NAME              43 (SETS)

 127            LOAD_BUILD_CLASS
                PUSH_NULL
                LOAD_CONST              40 (<code object Class1 at 0x000002E07A722F30, file "./OPz.py", line 127>)
                MAKE_FUNCTION
                LOAD_CONST              41 ('Class1')
                CALL                     2
                STORE_NAME              44 (Class1)

 142            LOAD_BUILD_CLASS
                PUSH_NULL
                LOAD_CONST              42 (<code object Class2 at 0x000002E07A729890, file "./OPz.py", line 142>)
                MAKE_FUNCTION
                LOAD_CONST              43 ('Class2')
                CALL                     2
                STORE_NAME              45 (Class2)

 153            LOAD_NAME               44 (Class1)
                PUSH_NULL
                CALL                     0
                STORE_NAME              46 (obj_1)

 154            LOAD_NAME               45 (Class2)
                PUSH_NULL
                CALL                     0
                STORE_NAME              47 (obj_2)

 156            LOAD_CONST              44 (<code object Uu at 0x000002E07A4D3E10, file "./OPz.py", line 156>)
                MAKE_FUNCTION
                STORE_NAME              48 (Uu)

 166            LOAD_CONST              45 (<code object uU at 0x000002E07A873BC0, file "./OPz.py", line 166>)
                MAKE_FUNCTION
                STORE_NAME              49 (uU)

 201            LOAD_CONST              46 (<code object UU at 0x000002E07A864590, file "./OPz.py", line 201>)
                MAKE_FUNCTION
                STORE_NAME              50 (UU)

 232            LOAD_CONST              47 (<code object UUu at 0x000002E07A7EA9E0, file "./OPz.py", line 232>)
                MAKE_FUNCTION
                STORE_NAME              51 (UUu)

 254            LOAD_CONST              48 (<code object you at 0x000002E07A502120, file "./OPz.py", line 254>)
                MAKE_FUNCTION
                STORE_NAME              52 (you)

 269            LOAD_CONST              49 (<code object intenTIONAL_FUNCS at 0x000002E07A756E50, file "./OPz.py", line 269>)
                MAKE_FUNCTION
                STORE_NAME              53 (intenTIONAL_FUNCS)

 310            LOAD_NAME               20 (STRINGS)
                LOAD_CONST              50 (5)
                BINARY_OP                5 (*)

 311            LOAD_NAME               23 (NUMBERS)
                LOAD_CONST              23 (3)
                BINARY_OP                5 (*)

 312            LOAD_NAME               25 (Xx)
                LOAD_NAME               27 (xX)
                LOAD_NAME               28 (XX)
                LOAD_NAME               32 (XXx)
                BUILD_LIST               4

 313            LOAD_NAME               34 (RND1)
                LOAD_CONST              21 (2)
                BINARY_OP                5 (*)

 314            LOAD_NAME               41 (TUPLES)
                LOAD_CONST              21 (2)
                BINARY_OP                5 (*)

 315            LOAD_NAME               43 (SETS)
                LOAD_CONST              23 (3)
                BINARY_OP                5 (*)

 309            LOAD_CONST              51 (('strings', 'numbers', 'dicts', 'lists', 'tuples', 'sets'))
                BUILD_CONST_KEY_MAP      6
                STORE_NAME              54 (MEGA_DUMMY_DATA)

 318            LOAD_CONST              52 (<code object Dd at 0x000002E07A898D90, file "./OPz.py", line 318>)
                MAKE_FUNCTION
                STORE_NAME              55 (Dd)

 336            LOAD_NAME               56 (__name__)
                LOAD_CONST              53 ('__main__')
                COMPARE_OP              88 (bool(==))
                POP_JUMP_IF_FALSE       97 (to L46)

 337            LOAD_NAME               53 (intenTIONAL_FUNCS)
                PUSH_NULL
                CALL                     0
                STORE_NAME              57 (dummy_additional)

 338            LOAD_NAME               55 (Dd)
                PUSH_NULL
                CALL                     0
                STORE_NAME              58 (dummy_final)

 339            LOAD_NAME               59 (print)
                PUSH_NULL
                LOAD_CONST              54 ('Ready for input.')
                CALL                     1
                POP_TOP

 340            LOAD_NAME               60 (input)
                PUSH_NULL
                LOAD_CONST              55 ('Enter the flag: ')
                CALL                     1
                STORE_NAME              61 (user_input)

 341            LOAD_NAME               52 (you)
                PUSH_NULL
                LOAD_NAME               61 (user_input)
                CALL                     1
                TO_BOOL
                POP_JUMP_IF_FALSE       45 (to L45)

 342            LOAD_NAME               59 (print)
                PUSH_NULL
                LOAD_CONST              56 ("\nCongratulations! That's the correct flag!")
                CALL                     1
                POP_TOP

 343            LOAD_NAME               59 (print)
                PUSH_NULL
                LOAD_CONST              57 ('Flag: ')
                LOAD_NAME               61 (user_input)
                FORMAT_SIMPLE
                BUILD_STRING             2
                CALL                     1
                POP_TOP

 344            LOAD_NAME               59 (print)
                PUSH_NULL
                LOAD_CONST              58 ('Verification hash: ')
                LOAD_NAME               35 (hash_function_1)
                PUSH_NULL
                LOAD_NAME               61 (user_input)
                CALL                     1
                FORMAT_SIMPLE
                BUILD_STRING             2
                CALL                     1
                POP_TOP

 345            LOAD_NAME               59 (print)
                PUSH_NULL
                LOAD_CONST              59 ('Cryptographic validation passed!')
                CALL                     1
                POP_TOP
                RETURN_CONST             1 (None)

 347   L45:     LOAD_NAME               59 (print)
                PUSH_NULL
                LOAD_CONST              60 ('\nIncorrect flag. Please try again.')
                CALL                     1
                POP_TOP
                RETURN_CONST             1 (None)

 336   L46:     RETURN_CONST             1 (None)

  --   L47:     SWAP                     2
                POP_TOP

  31            SWAP                     2
                STORE_FAST               0 (i)
                RERAISE                  0

  --   L48:     SWAP                     2
                POP_TOP

  31            SWAP                     2
                STORE_FAST               0 (i)
                RERAISE                  0

  --   L49:     SWAP                     2
                POP_TOP

  31            SWAP                     2
                STORE_FAST               0 (i)
                RERAISE                  0

  --   L50:     SWAP                     2
                POP_TOP

  33            SWAP                     2
                STORE_FAST               0 (i)
                RERAISE                  0

  --   L51:     SWAP                     2
                POP_TOP

  34            SWAP                     2
                STORE_FAST               0 (i)
                RERAISE                  0

  --   L52:     SWAP                     2
                POP_TOP

  35            SWAP                     2
                STORE_FAST               0 (i)
                RERAISE                  0

  --   L53:     SWAP                     2
                POP_TOP

  36            SWAP                     2
                STORE_FAST               0 (i)
                RERAISE                  0

  --   L54:     SWAP                     2
                POP_TOP

  39            SWAP                     2
                STORE_FAST               1 (_)
                RERAISE                  0

  --   L55:     SWAP                     2
                POP_TOP

  38            SWAP                     2
                STORE_FAST               1 (_)
                RERAISE                  0

  --   L56:     SWAP                     2
                POP_TOP

 124            SWAP                     2
                STORE_FAST               0 (i)
                RERAISE                  0

  --   L57:     SWAP                     2
                POP_TOP

 125            SWAP                     2
                STORE_FAST               0 (i)
                RERAISE                  0
ExceptionTable:
  L1 to L4 -> L47 [3]
  L5 to L8 -> L48 [3]
  L9 to L12 -> L49 [3]
  L13 to L16 -> L50 [2]
  L17 to L20 -> L51 [2]
  L21 to L24 -> L52 [2]
  L25 to L28 -> L53 [2]
  L29 to L31 -> L55 [2]
  L31 to L34 -> L54 [5]
  L34 to L36 -> L55 [2]
  L37 to L40 -> L56 [2]
  L41 to L44 -> L57 [2]
  L54 to L55 -> L55 [2]

Disassembly of <code object hash_function_1 at 0x000002E07A775160, file "./OPz.py", line 42>:
 42           RESUME                   0

 43           LOAD_CONST               1 (0)
              STORE_FAST               1 (result)

 44           LOAD_GLOBAL              1 (enumerate + NULL)
              LOAD_GLOBAL              3 (str + NULL)
              LOAD_FAST                0 (data)
              CALL                     1
              CALL                     1
              GET_ITER
      L1:     FOR_ITER                69 (to L4)
              UNPACK_SEQUENCE          2
              STORE_FAST_STORE_FAST   35 (i, char)

 45           LOAD_FAST                1 (result)
              LOAD_GLOBAL              5 (ord + NULL)
              LOAD_FAST                3 (char)
              CALL                     1
              LOAD_FAST                2 (i)
              LOAD_CONST               2 (1)
              BINARY_OP                0 (+)
              BINARY_OP                5 (*)
              BINARY_OP               13 (+=)
              STORE_FAST               1 (result)

 46           LOAD_FAST                1 (result)
              LOAD_CONST               3 (31)
              BINARY_OP                5 (*)
              LOAD_CONST               4 (982451653)
              BINARY_OP                6 (%)
              STORE_FAST               1 (result)

 47           LOAD_FAST                2 (i)
              LOAD_CONST               5 (7)
              BINARY_OP                6 (%)
              LOAD_CONST               1 (0)
              COMPARE_OP              88 (bool(==))
              POP_JUMP_IF_FALSE        5 (to L2)

 48           LOAD_FAST                1 (result)
              LOAD_CONST               6 (3735928559)
              BINARY_OP               25 (^=)
              STORE_FAST               1 (result)

 49   L2:     LOAD_FAST                2 (i)
              LOAD_CONST               7 (13)
              BINARY_OP                6 (%)
              LOAD_CONST               1 (0)
              COMPARE_OP              88 (bool(==))
              POP_JUMP_IF_TRUE         2 (to L3)
              JUMP_BACKWARD           58 (to L1)

 50   L3:     LOAD_FAST                1 (result)
              LOAD_CONST               8 (3)
              BINARY_OP                3 (<<)
              LOAD_FAST                1 (result)
              LOAD_CONST               9 (29)
              BINARY_OP                9 (>>)
              BINARY_OP                7 (|)
              STORE_FAST               1 (result)
              JUMP_BACKWARD           71 (to L1)

 44   L4:     END_FOR
              POP_TOP

 51           LOAD_FAST                1 (result)
              RETURN_VALUE

Disassembly of <code object hash_function_2 at 0x000002E07A4D23F0, file "./OPz.py", line 53>:
 53           RESUME                   0

 54           LOAD_GLOBAL              0 (hashlib)
              LOAD_ATTR                2 (sha256)
              PUSH_NULL
              LOAD_GLOBAL              5 (str + NULL)
              LOAD_FAST                0 (data)
              CALL                     1
              LOAD_ATTR                7 (encode + NULL|self)
              CALL                     0
              CALL                     1
              STORE_FAST               1 (h)

 55           LOAD_GLOBAL              9 (int + NULL)
              LOAD_FAST                1 (h)
              LOAD_ATTR               11 (hexdigest + NULL|self)
              CALL                     0
              LOAD_CONST               0 (None)
              LOAD_CONST               1 (8)
              BINARY_SLICE
              LOAD_CONST               2 (16)
              CALL                     2
              RETURN_VALUE

Disassembly of <code object string_manipulator at 0x000002E07A501D40, file "./OPz.py", line 57>:
 57           RESUME                   0

 58           LOAD_CONST               1 ('')
              STORE_FAST               1 (result)

 59           LOAD_GLOBAL              1 (enumerate + NULL)
              LOAD_FAST                0 (s)
              CALL                     1
              GET_ITER
      L1:     FOR_ITER                74 (to L3)
              UNPACK_SEQUENCE          2
              STORE_FAST_STORE_FAST   35 (i, c)

 60           LOAD_FAST                2 (i)
              LOAD_CONST               2 (2)
              BINARY_OP                6 (%)
              LOAD_CONST               3 (0)
              COMPARE_OP              88 (bool(==))
              POP_JUMP_IF_FALSE       31 (to L2)

 61           LOAD_FAST                1 (result)
              LOAD_GLOBAL              3 (chr + NULL)
              LOAD_GLOBAL              5 (ord + NULL)
              LOAD_FAST                3 (c)
              CALL                     1
              LOAD_CONST               4 (13)
              BINARY_OP                0 (+)
              LOAD_CONST               5 (256)
              BINARY_OP                6 (%)
              CALL                     1
              BINARY_OP               13 (+=)
              STORE_FAST               1 (result)
              JUMP_BACKWARD           45 (to L1)

 63   L2:     LOAD_FAST                1 (result)
              LOAD_GLOBAL              3 (chr + NULL)
              LOAD_GLOBAL              5 (ord + NULL)
              LOAD_FAST                3 (c)
              CALL                     1
              LOAD_CONST               6 (7)
              BINARY_OP               10 (-)
              LOAD_CONST               5 (256)
              BINARY_OP                6 (%)
              CALL                     1
              BINARY_OP               13 (+=)
              STORE_FAST               1 (result)
              JUMP_BACKWARD           76 (to L1)

 59   L3:     END_FOR
              POP_TOP

 64           LOAD_GLOBAL              6 (base64)
              LOAD_ATTR                8 (b64encode)
              PUSH_NULL
              LOAD_FAST                1 (result)
              LOAD_ATTR               11 (encode + NULL|self)
              CALL                     0
              CALL                     1
              LOAD_ATTR               13 (decode + NULL|self)
              CALL                     0
              RETURN_VALUE

Disassembly of <code object operations at 0x000002E07A547280, file "./OPz.py", line 66>:
 66           RESUME                   0

 67           BUILD_LIST               0
              STORE_FAST               0 (results)

 68           LOAD_GLOBAL              1 (range + NULL)
              LOAD_CONST               1 (1000)
              CALL                     1
              GET_ITER
      L1:     FOR_ITER                47 (to L2)
              STORE_FAST               1 (i)

 69           LOAD_FAST                1 (i)
              LOAD_CONST               2 (17)
              BINARY_OP                5 (*)
              LOAD_CONST               3 (23)
              BINARY_OP                0 (+)
              LOAD_CONST               4 (97)
              BINARY_OP                6 (%)
              STORE_FAST               2 (val)

 70           LOAD_FAST                2 (val)
              LOAD_CONST               5 (3)
              BINARY_OP                8 (**)
              LOAD_CONST               6 (1009)
              BINARY_OP                6 (%)
              STORE_FAST               2 (val)

 71           LOAD_FAST                2 (val)
              LOAD_CONST               7 (31)
              BINARY_OP                0 (+)
              LOAD_CONST               8 (7)
              BINARY_OP                5 (*)
              STORE_FAST               2 (val)

 72           LOAD_FAST                0 (results)
              LOAD_ATTR                3 (append + NULL|self)
              LOAD_FAST                2 (val)
              CALL                     1
              POP_TOP
              JUMP_BACKWARD           49 (to L1)

 68   L2:     END_FOR
              POP_TOP

 73           LOAD_GLOBAL              5 (sum + NULL)
              LOAD_FAST                0 (results)
              CALL                     1
              LOAD_CONST               9 (999983)
              BINARY_OP                6 (%)
              RETURN_VALUE

Disassembly of <code object CONSTRAINTSS at 0x000002E07A867D40, file "./OPz.py", line 75>:
  75            RESUME                   0

  76            LOAD_GLOBAL              1 (range + NULL)
                LOAD_FAST                1 (num_vars)
                CALL                     1
                GET_ITER
                LOAD_FAST_AND_CLEAR      2 (i)
                SWAP                     2
        L1:     BUILD_LIST               0
                SWAP                     2
                GET_ITER
        L2:     FOR_ITER                28 (to L3)
                STORE_FAST               2 (i)
                LOAD_GLOBAL              2 (z3)
                LOAD_ATTR                4 (Int)
                PUSH_NULL
                LOAD_CONST               1 ('dummy_')
                LOAD_FAST                2 (i)
                FORMAT_SIMPLE
                BUILD_STRING             2
                CALL                     1
                LIST_APPEND              2
                JUMP_BACKWARD           30 (to L2)
        L3:     END_FOR
                POP_TOP
        L4:     STORE_FAST               3 (dummy_vars)
                STORE_FAST               2 (i)

  78            LOAD_GLOBAL              1 (range + NULL)
                LOAD_CONST               2 (0)
                LOAD_FAST                1 (num_vars)
                LOAD_CONST               3 (1)
                BINARY_OP               10 (-)
                LOAD_CONST               4 (2)
                CALL                     3
                GET_ITER
        L5:     FOR_ITER               107 (to L6)
                STORE_FAST               2 (i)

  79            LOAD_FAST                0 (solver)
                LOAD_ATTR                7 (add + NULL|self)
                LOAD_FAST_LOAD_FAST     50 (dummy_vars, i)
                BINARY_SUBSCR
                LOAD_FAST_LOAD_FAST     50 (dummy_vars, i)
                LOAD_CONST               3 (1)
                BINARY_OP                0 (+)
                BINARY_SUBSCR
                BINARY_OP                0 (+)
                LOAD_CONST               5 (42)
                COMPARE_OP              72 (==)
                CALL                     1
                POP_TOP

  80            LOAD_FAST                0 (solver)
                LOAD_ATTR                7 (add + NULL|self)
                LOAD_FAST_LOAD_FAST     50 (dummy_vars, i)
                BINARY_SUBSCR
                LOAD_CONST               4 (2)
                BINARY_OP                5 (*)
                LOAD_FAST_LOAD_FAST     50 (dummy_vars, i)
                LOAD_CONST               3 (1)
                BINARY_OP                0 (+)
                BINARY_SUBSCR
                COMPARE_OP              72 (==)
                CALL                     1
                POP_TOP

  81            LOAD_FAST                0 (solver)
                LOAD_ATTR                7 (add + NULL|self)
                LOAD_FAST_LOAD_FAST     50 (dummy_vars, i)
                BINARY_SUBSCR
                LOAD_CONST               2 (0)
                COMPARE_OP             172 (>=)
                CALL                     1
                POP_TOP

  82            LOAD_FAST                0 (solver)
                LOAD_ATTR                7 (add + NULL|self)
                LOAD_FAST_LOAD_FAST     50 (dummy_vars, i)
                BINARY_SUBSCR
                LOAD_CONST               6 (100)
                COMPARE_OP              42 (<=)
                CALL                     1
                POP_TOP
                JUMP_BACKWARD          109 (to L5)

  78    L6:     END_FOR
                POP_TOP

  84            LOAD_GLOBAL              1 (range + NULL)
                LOAD_CONST               7 (10)
                CALL                     1
                GET_ITER
        L7:     FOR_ITER                89 (to L9)
                STORE_FAST               2 (i)

  85            LOAD_FAST                2 (i)
                LOAD_CONST               8 (3)
                BINARY_OP                5 (*)
                LOAD_FAST                2 (i)
                LOAD_CONST               8 (3)
                BINARY_OP                5 (*)
                LOAD_CONST               3 (1)
                BINARY_OP                0 (+)
                LOAD_FAST                2 (i)
                LOAD_CONST               8 (3)
                BINARY_OP                5 (*)
                LOAD_CONST               4 (2)
                BINARY_OP                0 (+)
                STORE_FAST_STORE_FAST  101 (idx3, idx2)
                STORE_FAST               4 (idx1)

  86            LOAD_FAST_LOAD_FAST     97 (idx3, num_vars)
                COMPARE_OP              18 (bool(<))
                POP_JUMP_IF_TRUE         2 (to L8)
                JUMP_BACKWARD           30 (to L7)

  87    L8:     LOAD_FAST                0 (solver)
                LOAD_ATTR                7 (add + NULL|self)
                LOAD_FAST_LOAD_FAST     52 (dummy_vars, idx1)
                BINARY_SUBSCR
                LOAD_FAST_LOAD_FAST     53 (dummy_vars, idx2)
                BINARY_SUBSCR
                BINARY_OP                0 (+)
                LOAD_FAST_LOAD_FAST     54 (dummy_vars, idx3)
                BINARY_SUBSCR
                LOAD_CONST               7 (10)
                BINARY_OP                0 (+)
                COMPARE_OP              72 (==)
                CALL                     1
                POP_TOP

  88            LOAD_FAST                0 (solver)
                LOAD_ATTR                7 (add + NULL|self)
                LOAD_FAST_LOAD_FAST     52 (dummy_vars, idx1)
                BINARY_SUBSCR
                LOAD_FAST_LOAD_FAST     53 (dummy_vars, idx2)
                BINARY_SUBSCR
                BINARY_OP               10 (-)
                LOAD_CONST               9 (5)
                COMPARE_OP              72 (==)
                CALL                     1
                POP_TOP
                JUMP_BACKWARD           91 (to L7)

  84    L9:     END_FOR
                POP_TOP
                RETURN_CONST             0 (None)

  --   L10:     SWAP                     2
                POP_TOP

  76            SWAP                     2
                STORE_FAST               2 (i)
                RERAISE                  0
ExceptionTable:
  L1 to L4 -> L10 [2]

Disassembly of <code object CALCSS at 0x000002E07A8991A0, file "./OPz.py", line 90>:
  --            MAKE_CELL               12 (i)
                MAKE_CELL               13 (j)
                MAKE_CELL               14 (matrix_a)
                MAKE_CELL               15 (matrix_b)

  90            RESUME                   0

  91            LOAD_GLOBAL              1 (range + NULL)
                LOAD_CONST               1 (20)
                CALL                     1
                GET_ITER
                LOAD_FAST_AND_CLEAR      0 (_)
                SWAP                     2
        L1:     BUILD_LIST               0
                SWAP                     2
                GET_ITER
        L2:     FOR_ITER                52 (to L7)
                STORE_FAST               0 (_)
                LOAD_GLOBAL              1 (range + NULL)
                LOAD_CONST               1 (20)
                CALL                     1
                GET_ITER
                LOAD_FAST_AND_CLEAR      0 (_)
                SWAP                     2
        L3:     BUILD_LIST               0
                SWAP                     2
                GET_ITER
        L4:     FOR_ITER                26 (to L5)
                STORE_FAST               0 (_)
                LOAD_GLOBAL              2 (random)
                LOAD_ATTR                4 (randint)
                PUSH_NULL
                LOAD_CONST               2 (1)
                LOAD_CONST               3 (10)
                CALL                     2
                LIST_APPEND              2
                JUMP_BACKWARD           28 (to L4)
        L5:     END_FOR
                POP_TOP
        L6:     SWAP                     2
                STORE_FAST               0 (_)
                LIST_APPEND              2
                JUMP_BACKWARD           54 (to L2)
        L7:     END_FOR
                POP_TOP
        L8:     SWAP                     2
                STORE_FAST               0 (_)
                STORE_DEREF             14 (matrix_a)

  92            LOAD_GLOBAL              1 (range + NULL)
                LOAD_CONST               1 (20)
                CALL                     1
                GET_ITER
                LOAD_FAST_AND_CLEAR      0 (_)
                SWAP                     2
        L9:     BUILD_LIST               0
                SWAP                     2
                GET_ITER
       L10:     FOR_ITER                52 (to L15)
                STORE_FAST               0 (_)
                LOAD_GLOBAL              1 (range + NULL)
                LOAD_CONST               1 (20)
                CALL                     1
                GET_ITER
                LOAD_FAST_AND_CLEAR      0 (_)
                SWAP                     2
       L11:     BUILD_LIST               0
                SWAP                     2
                GET_ITER
       L12:     FOR_ITER                26 (to L13)
                STORE_FAST               0 (_)
                LOAD_GLOBAL              2 (random)
                LOAD_ATTR                4 (randint)
                PUSH_NULL
                LOAD_CONST               2 (1)
                LOAD_CONST               3 (10)
                CALL                     2
                LIST_APPEND              2
                JUMP_BACKWARD           28 (to L12)
       L13:     END_FOR
                POP_TOP
       L14:     SWAP                     2
                STORE_FAST               0 (_)
                LIST_APPEND              2
                JUMP_BACKWARD           54 (to L10)
       L15:     END_FOR
                POP_TOP
       L16:     SWAP                     2
                STORE_FAST               0 (_)
                STORE_DEREF             15 (matrix_b)

  94            BUILD_LIST               0
                STORE_FAST               1 (result_matrix)

  95            LOAD_GLOBAL              1 (range + NULL)
                LOAD_CONST               1 (20)
                CALL                     1
                GET_ITER
       L17:     FOR_ITER                90 (to L20)
                STORE_DEREF             12 (i)

  96            BUILD_LIST               0
                STORE_FAST               2 (row)

  97            LOAD_GLOBAL              1 (range + NULL)
                LOAD_CONST               1 (20)
                CALL                     1
                GET_ITER
       L18:     FOR_ITER                53 (to L19)
                STORE_DEREF             13 (j)

  98            LOAD_GLOBAL              7 (sum + NULL)
                LOAD_FAST               12 (i)
                LOAD_FAST               13 (j)
                LOAD_FAST               14 (matrix_a)
                LOAD_FAST               15 (matrix_b)
                BUILD_TUPLE              4
                LOAD_CONST               4 (<code object <genexpr> at 0x000002E07A741F00, file "./OPz.py", line 98>)
                MAKE_FUNCTION
                SET_FUNCTION_ATTRIBUTE   8 (closure)
                LOAD_GLOBAL              1 (range + NULL)
                LOAD_CONST               1 (20)
                CALL                     1
                GET_ITER
                CALL                     0
                CALL                     1
                STORE_FAST               3 (val)

  99            LOAD_FAST                2 (row)
                LOAD_ATTR                9 (append + NULL|self)
                LOAD_FAST                3 (val)
                CALL                     1
                POP_TOP
                JUMP_BACKWARD           55 (to L18)

  97   L19:     END_FOR
                POP_TOP

 100            LOAD_FAST                1 (result_matrix)
                LOAD_ATTR                9 (append + NULL|self)
                LOAD_FAST                2 (row)
                CALL                     1
                POP_TOP
                JUMP_BACKWARD           92 (to L17)

  95   L20:     END_FOR
                POP_TOP

 102            LOAD_CONST               5 ('')
                LOAD_ATTR               11 (join + NULL|self)
                LOAD_GLOBAL             12 (STRINGS)
                CALL                     1
                STORE_FAST               4 (dummy_text)

 103            LOAD_CONST               5 ('')
                STORE_FAST               5 (processed)

 104            LOAD_FAST                4 (dummy_text)
                LOAD_CONST               0 (None)
                LOAD_CONST               6 (10000)
                BINARY_SLICE
                GET_ITER
       L21:     FOR_ITER                37 (to L22)
                STORE_FAST               6 (char)

 105            LOAD_GLOBAL             15 (ord + NULL)
                LOAD_FAST                6 (char)
                CALL                     1
                STORE_FAST               7 (ascii_val)

 106            LOAD_FAST                5 (processed)
                LOAD_GLOBAL             17 (chr + NULL)
                LOAD_FAST                7 (ascii_val)
                LOAD_CONST               7 (3)
                BINARY_OP                5 (*)
                LOAD_CONST               8 (7)
                BINARY_OP                0 (+)
                LOAD_CONST               9 (256)
                BINARY_OP                6 (%)
                CALL                     1
                BINARY_OP               13 (+=)
                STORE_FAST               5 (processed)
                JUMP_BACKWARD           39 (to L21)

 104   L22:     END_FOR
                POP_TOP

 108            LOAD_CONST               2 (1)
                LOAD_CONST               2 (1)
                BUILD_LIST               2
                STORE_FAST               8 (fibonacci)

 109            LOAD_GLOBAL              1 (range + NULL)
                LOAD_CONST              10 (100)
                CALL                     1
                GET_ITER
       L23:     FOR_ITER                29 (to L24)
                STORE_DEREF             12 (i)

 110            LOAD_FAST                8 (fibonacci)
                LOAD_ATTR                9 (append + NULL|self)
                LOAD_FAST                8 (fibonacci)
                LOAD_CONST              11 (-1)
                BINARY_SUBSCR
                LOAD_FAST                8 (fibonacci)
                LOAD_CONST              12 (-2)
                BINARY_SUBSCR
                BINARY_OP                0 (+)
                CALL                     1
                POP_TOP
                JUMP_BACKWARD           31 (to L23)

 109   L24:     END_FOR
                POP_TOP

 112            BUILD_LIST               0
                STORE_FAST               9 (prime_numbers)

 113            LOAD_GLOBAL              1 (range + NULL)
                LOAD_CONST              13 (2)
                LOAD_CONST              14 (1000)
                CALL                     2
                GET_ITER
       L25:     FOR_ITER                78 (to L31)
                STORE_FAST              10 (num)

 114            LOAD_CONST              15 (True)
                STORE_FAST              11 (is_prime)

 115            LOAD_GLOBAL              1 (range + NULL)
                LOAD_CONST              13 (2)
                LOAD_GLOBAL             19 (int + NULL)
                LOAD_FAST               10 (num)
                LOAD_CONST              16 (0.5)
                BINARY_OP                8 (**)
                CALL                     1
                LOAD_CONST               2 (1)
                BINARY_OP                0 (+)
                CALL                     2
                GET_ITER
       L26:     FOR_ITER                16 (to L28)
                STORE_DEREF             12 (i)

 116            LOAD_FAST               10 (num)
                LOAD_DEREF              12 (i)
                BINARY_OP                6 (%)
                LOAD_CONST              17 (0)
                COMPARE_OP              88 (bool(==))
                POP_JUMP_IF_TRUE         2 (to L27)
                JUMP_BACKWARD           14 (to L26)

 117   L27:     LOAD_CONST              18 (False)
                STORE_FAST              11 (is_prime)

 118            POP_TOP
                JUMP_FORWARD             2 (to L29)

 115   L28:     END_FOR
                POP_TOP

 119   L29:     LOAD_FAST               11 (is_prime)
                TO_BOOL
                POP_JUMP_IF_TRUE         2 (to L30)
                JUMP_BACKWARD           61 (to L25)

 120   L30:     LOAD_FAST                9 (prime_numbers)
                LOAD_ATTR                9 (append + NULL|self)
                LOAD_FAST               10 (num)
                CALL                     1
                POP_TOP
                JUMP_BACKWARD           80 (to L25)

 113   L31:     END_FOR
                POP_TOP

 122            LOAD_GLOBAL             21 (len + NULL)
                LOAD_FAST                1 (result_matrix)
                CALL                     1
                LOAD_GLOBAL             21 (len + NULL)
                LOAD_FAST                5 (processed)
                CALL                     1
                LOAD_GLOBAL             21 (len + NULL)
                LOAD_FAST                8 (fibonacci)
                CALL                     1
                LOAD_GLOBAL             21 (len + NULL)
                LOAD_FAST                9 (prime_numbers)
                CALL                     1
                BUILD_TUPLE              4
                RETURN_VALUE

  --   L32:     SWAP                     2
                POP_TOP

  91            SWAP                     2
                STORE_FAST               0 (_)
                RERAISE                  0

  --   L33:     SWAP                     2
                POP_TOP

  91            SWAP                     2
                STORE_FAST               0 (_)
                RERAISE                  0

  --   L34:     SWAP                     2
                POP_TOP

  92            SWAP                     2
                STORE_FAST               0 (_)
                RERAISE                  0

  --   L35:     SWAP                     2
                POP_TOP

  92            SWAP                     2
                STORE_FAST               0 (_)
                RERAISE                  0
ExceptionTable:
  L1 to L3 -> L33 [2]
  L3 to L6 -> L32 [5]
  L6 to L8 -> L33 [2]
  L9 to L11 -> L35 [2]
  L11 to L14 -> L34 [5]
  L14 to L16 -> L35 [2]
  L32 to L33 -> L33 [2]
  L34 to L35 -> L35 [2]

Disassembly of <code object <genexpr> at 0x000002E07A741F00, file "./OPz.py", line 98>:
  --           COPY_FREE_VARS           4

  98           RETURN_GENERATOR
               POP_TOP
       L1:     RESUME                   0
               LOAD_FAST                0 (.0)
               GET_ITER
       L2:     FOR_ITER                22 (to L3)
               STORE_FAST               1 (k)
               LOAD_DEREF               4 (matrix_a)
               LOAD_DEREF               2 (i)
               BINARY_SUBSCR
               LOAD_FAST                1 (k)
               BINARY_SUBSCR
               LOAD_DEREF               5 (matrix_b)
               LOAD_FAST                1 (k)
               BINARY_SUBSCR
               LOAD_DEREF               3 (j)
               BINARY_SUBSCR
               BINARY_OP                5 (*)
               YIELD_VALUE              0
               RESUME                   5
               POP_TOP
               JUMP_BACKWARD           24 (to L2)
       L3:     END_FOR
               POP_TOP
               RETURN_CONST             0 (None)

  --   L4:     CALL_INTRINSIC_1         3 (INTRINSIC_STOPITERATION_ERROR)
               RERAISE                  1
ExceptionTable:
  L1 to L4 -> L4 [0] lasti

Disassembly of <code object Class1 at 0x000002E07A722F30, file "./OPz.py", line 127>:
127           RESUME                   0
              LOAD_NAME                0 (__name__)
              STORE_NAME               1 (__module__)
              LOAD_CONST               0 ('Class1')
              STORE_NAME               2 (__qualname__)
              LOAD_CONST               1 (127)
              STORE_NAME               3 (__firstlineno__)

128           LOAD_CONST               2 (<code object __init__ at 0x000002E07A4D3730, file "./OPz.py", line 128>)
              MAKE_FUNCTION
              STORE_NAME               4 (__init__)

133           LOAD_CONST               3 (<code object dummy_method_1 at 0x000002E07A769B50, file "./OPz.py", line 133>)
              MAKE_FUNCTION
              STORE_NAME               5 (dummy_method_1)

136           LOAD_CONST               4 (<code object dummy_method_2 at 0x000002E07A748F30, file "./OPz.py", line 136>)
              MAKE_FUNCTION
              STORE_NAME               6 (dummy_method_2)

139           LOAD_CONST               5 (<code object dummy_method_3 at 0x000002E07A729A70, file "./OPz.py", line 139>)
              MAKE_FUNCTION
              STORE_NAME               7 (dummy_method_3)
              LOAD_CONST               6 (('data', 'numbers', 'strings'))
              STORE_NAME               8 (__static_attributes__)
              RETURN_CONST             7 (None)

Disassembly of <code object __init__ at 0x000002E07A4D3730, file "./OPz.py", line 128>:
 128           RESUME                   0

 129           LOAD_GLOBAL              1 (range + NULL)
               LOAD_CONST               1 (1000)
               CALL                     1
               GET_ITER
               LOAD_FAST_AND_CLEAR      1 (i)
               SWAP                     2
       L1:     BUILD_MAP                0
               SWAP                     2
               GET_ITER
       L2:     FOR_ITER                 8 (to L3)
               STORE_FAST_LOAD_FAST    17 (i, i)
               LOAD_FAST                1 (i)
               LOAD_CONST               2 (2)
               BINARY_OP                8 (**)
               MAP_ADD                  2
               JUMP_BACKWARD           10 (to L2)
       L3:     END_FOR
               POP_TOP
       L4:     SWAP                     2
               STORE_FAST               1 (i)
               LOAD_FAST                0 (self)
               STORE_ATTR               1 (data)

 130           LOAD_GLOBAL              4 (STRINGS)
               LOAD_CONST               0 (None)
               LOAD_CONST               3 (10)
               BINARY_SLICE
               LOAD_FAST                0 (self)
               STORE_ATTR               3 (strings)

 131           LOAD_GLOBAL              8 (NUMBERS)
               LOAD_CONST               0 (None)
               LOAD_CONST               1 (1000)
               BINARY_SLICE
               LOAD_FAST                0 (self)
               STORE_ATTR               5 (numbers)
               RETURN_CONST             0 (None)

  --   L5:     SWAP                     2
               POP_TOP

 129           SWAP                     2
               STORE_FAST               1 (i)
               RERAISE                  0
ExceptionTable:
  L1 to L4 -> L5 [2]

Disassembly of <code object dummy_method_1 at 0x000002E07A769B50, file "./OPz.py", line 133>:
133           RESUME                   0

134           LOAD_FAST                1 (x)
              LOAD_CONST               1 (17)
              BINARY_OP                5 (*)
              LOAD_CONST               2 (23)
              BINARY_OP                0 (+)
              LOAD_CONST               3 (97)
              BINARY_OP                6 (%)
              RETURN_VALUE

Disassembly of <code object dummy_method_2 at 0x000002E07A748F30, file "./OPz.py", line 136>:
136           RESUME                   0

137           LOAD_GLOBAL              0 (hashlib)
              LOAD_ATTR                2 (sha1)
              PUSH_NULL
              LOAD_GLOBAL              5 (str + NULL)
              LOAD_FAST                1 (x)
              CALL                     1
              LOAD_ATTR                7 (encode + NULL|self)
              CALL                     0
              CALL                     1
              LOAD_ATTR                9 (hexdigest + NULL|self)
              CALL                     0
              RETURN_VALUE

Disassembly of <code object dummy_method_3 at 0x000002E07A729A70, file "./OPz.py", line 139>:
139           RESUME                   0

140           LOAD_FAST_LOAD_FAST     18 (x, y)
              BINARY_OP                0 (+)
              LOAD_FAST_LOAD_FAST     18 (x, y)
              BINARY_OP               10 (-)
              BINARY_OP                5 (*)
              LOAD_FAST_LOAD_FAST     18 (x, y)
              BINARY_OP                5 (*)
              BINARY_OP                0 (+)
              RETURN_VALUE

Disassembly of <code object Class2 at 0x000002E07A729890, file "./OPz.py", line 142>:
142           RESUME                   0
              LOAD_NAME                0 (__name__)
              STORE_NAME               1 (__module__)
              LOAD_CONST               0 ('Class2')
              STORE_NAME               2 (__qualname__)
              LOAD_CONST               1 (142)
              STORE_NAME               3 (__firstlineno__)

143           LOAD_CONST               2 (<code object __init__ at 0x000002E07A4FDDF0, file "./OPz.py", line 143>)
              MAKE_FUNCTION
              STORE_NAME               4 (__init__)

147           LOAD_CONST               3 (<code object process_data at 0x000002E07A755B30, file "./OPz.py", line 147>)
              MAKE_FUNCTION
              STORE_NAME               5 (process_data)
              LOAD_CONST               4 (('lookup', 'matrix'))
              STORE_NAME               6 (__static_attributes__)
              RETURN_CONST             5 (None)

Disassembly of <code object __init__ at 0x000002E07A4FDDF0, file "./OPz.py", line 143>:
 143            RESUME                   0

 144            LOAD_GLOBAL              1 (range + NULL)
                LOAD_CONST               1 (50)
                CALL                     1
                GET_ITER
                LOAD_FAST_AND_CLEAR      1 (i)
                LOAD_FAST_AND_CLEAR      2 (j)
                SWAP                     3
        L1:     BUILD_LIST               0
                SWAP                     2
                GET_ITER
        L2:     FOR_ITER                33 (to L7)
                STORE_FAST               1 (i)
                LOAD_GLOBAL              1 (range + NULL)
                LOAD_CONST               1 (50)
                CALL                     1
                GET_ITER
                LOAD_FAST_AND_CLEAR      2 (j)
                SWAP                     2
        L3:     BUILD_LIST               0
                SWAP                     2
                GET_ITER
        L4:     FOR_ITER                 7 (to L5)
                STORE_FAST_LOAD_FAST    34 (j, j)
                LOAD_FAST                1 (i)
                BINARY_OP                5 (*)
                LIST_APPEND              2
                JUMP_BACKWARD            9 (to L4)
        L5:     END_FOR
                POP_TOP
        L6:     SWAP                     2
                STORE_FAST               2 (j)
                LIST_APPEND              2
                JUMP_BACKWARD           35 (to L2)
        L7:     END_FOR
                POP_TOP
        L8:     SWAP                     3
                STORE_FAST               2 (j)
                STORE_FAST               1 (i)
                LOAD_FAST                0 (self)
                STORE_ATTR               1 (matrix)

 145            LOAD_GLOBAL              1 (range + NULL)
                LOAD_CONST               2 (256)
                CALL                     1
                GET_ITER
                LOAD_FAST_AND_CLEAR      1 (i)
                SWAP                     2
        L9:     BUILD_MAP                0
                SWAP                     2
                GET_ITER
       L10:     FOR_ITER                15 (to L11)
                STORE_FAST               1 (i)
                LOAD_GLOBAL              5 (chr + NULL)
                LOAD_FAST                1 (i)
                CALL                     1
                LOAD_FAST                1 (i)
                MAP_ADD                  2
                JUMP_BACKWARD           17 (to L10)
       L11:     END_FOR
                POP_TOP
       L12:     SWAP                     2
                STORE_FAST               1 (i)
                LOAD_FAST                0 (self)
                STORE_ATTR               3 (lookup)
                RETURN_CONST             0 (None)

  --   L13:     SWAP                     2
                POP_TOP

 144            SWAP                     2
                STORE_FAST               2 (j)
                RERAISE                  0

  --   L14:     SWAP                     2
                POP_TOP

 144            SWAP                     3
                STORE_FAST               2 (j)
                STORE_FAST               1 (i)
                RERAISE                  0

  --   L15:     SWAP                     2
                POP_TOP

 145            SWAP                     2
                STORE_FAST               1 (i)
                RERAISE                  0
ExceptionTable:
  L1 to L3 -> L14 [3]
  L3 to L6 -> L13 [6]
  L6 to L8 -> L14 [3]
  L9 to L12 -> L15 [2]
  L13 to L14 -> L14 [3]

Disassembly of <code object process_data at 0x000002E07A755B30, file "./OPz.py", line 147>:
147           RESUME                   0

148           LOAD_CONST               1 (0)
              STORE_FAST               2 (result)

149           LOAD_FAST                1 (data)
              GET_ITER
      L1:     FOR_ITER                29 (to L2)
              STORE_FAST               3 (item)

150           LOAD_FAST                2 (result)
              LOAD_GLOBAL              1 (hash + NULL)
              LOAD_GLOBAL              3 (str + NULL)
              LOAD_FAST                3 (item)
              CALL                     1
              CALL                     1
              LOAD_CONST               2 (1000)
              BINARY_OP                6 (%)
              BINARY_OP               13 (+=)
              STORE_FAST               2 (result)
              JUMP_BACKWARD           31 (to L1)

149   L2:     END_FOR
              POP_TOP

151           LOAD_FAST                2 (result)
              RETURN_VALUE

Disassembly of <code object Uu at 0x000002E07A4D3E10, file "./OPz.py", line 156>:
156           RESUME                   0

157           LOAD_FAST                0 (f)
              LOAD_CONST               1 (0)
              BINARY_SUBSCR
              LOAD_CONST               2 (102)
              COMPARE_OP              88 (bool(==))
              POP_JUMP_IF_TRUE         1 (to L1)
              RETURN_CONST             3 (False)

158   L1:     LOAD_FAST                0 (f)
              LOAD_CONST               4 (1)
              BINARY_SUBSCR
              LOAD_CONST               5 (108)
              COMPARE_OP              88 (bool(==))
              POP_JUMP_IF_TRUE         1 (to L2)
              RETURN_CONST             3 (False)

159   L2:     LOAD_FAST                0 (f)
              LOAD_CONST               6 (2)
              BINARY_SUBSCR
              LOAD_CONST               7 (97)
              COMPARE_OP              88 (bool(==))
              POP_JUMP_IF_TRUE         1 (to L3)
              RETURN_CONST             3 (False)

160   L3:     LOAD_FAST                0 (f)
              LOAD_CONST               8 (3)
              BINARY_SUBSCR
              LOAD_CONST               9 (103)
              COMPARE_OP              88 (bool(==))
              POP_JUMP_IF_TRUE         1 (to L4)
              RETURN_CONST             3 (False)

161   L4:     LOAD_FAST                0 (f)
              LOAD_CONST              10 (4)
              BINARY_SUBSCR
              LOAD_CONST              11 (123)
              COMPARE_OP              88 (bool(==))
              POP_JUMP_IF_TRUE         1 (to L5)
              RETURN_CONST             3 (False)

162   L5:     LOAD_FAST                0 (f)
              LOAD_CONST              12 (5)
              BINARY_SUBSCR
              LOAD_CONST              13 (85)
              COMPARE_OP              88 (bool(==))
              POP_JUMP_IF_TRUE         1 (to L6)
              RETURN_CONST             3 (False)

163   L6:     LOAD_FAST                0 (f)
              LOAD_CONST              14 (6)
              BINARY_SUBSCR
              LOAD_CONST              15 (95)
              COMPARE_OP              88 (bool(==))
              POP_JUMP_IF_TRUE         1 (to L7)
              RETURN_CONST             3 (False)

164   L7:     RETURN_CONST            16 (True)

Disassembly of <code object uU at 0x000002E07A873BC0, file "./OPz.py", line 166>:
 166            RESUME                   0

 167            NOP

 168    L1:     LOAD_FAST                0 (f)
                LOAD_CONST               1 (7)
                BINARY_SUBSCR
                LOAD_CONST               1 (7)
                BINARY_OP                5 (*)
                LOAD_CONST               2 (525)
                BINARY_OP               10 (-)
                LOAD_CONST               3 (0)
                COMPARE_OP             119 (bool(!=))
                POP_JUMP_IF_FALSE        1 (to L3)

 169    L2:     RETURN_CONST             4 (False)

 171    L3:     LOAD_FAST                0 (f)
                LOAD_CONST               5 (8)
                BINARY_SUBSCR
                LOAD_CONST               6 (17)
                BINARY_OP                5 (*)
                LOAD_CONST               7 (10)
                BINARY_OP               10 (-)
                LOAD_CONST               8 (933)
                BINARY_OP               12 (^)
                LOAD_CONST               9 (252)
                COMPARE_OP             119 (bool(!=))
                POP_JUMP_IF_FALSE        1 (to L5)

 172    L4:     RETURN_CONST             4 (False)

 174    L5:     LOAD_FAST                0 (f)
                LOAD_CONST              10 (9)
                BINARY_SUBSCR
                LOAD_FAST                0 (f)
                LOAD_CONST               5 (8)
                BINARY_SUBSCR
                BINARY_OP               10 (-)
                LOAD_CONST              11 (2)
                BINARY_OP                8 (**)
                LOAD_FAST                0 (f)
                LOAD_CONST              12 (28)
                BINARY_SUBSCR
                LOAD_FAST                0 (f)
                LOAD_CONST               5 (8)
                BINARY_SUBSCR
                BINARY_OP               10 (-)
                LOAD_CONST              11 (2)
                BINARY_OP                8 (**)
                BINARY_OP                0 (+)
                LOAD_FAST                0 (f)
                LOAD_CONST              13 (31)
                BINARY_SUBSCR
                LOAD_FAST                0 (f)
                LOAD_CONST               5 (8)
                BINARY_SUBSCR
                BINARY_OP               10 (-)
                LOAD_CONST              11 (2)
                BINARY_OP                8 (**)
                BINARY_OP                0 (+)
                LOAD_CONST               3 (0)
                COMPARE_OP             119 (bool(!=))
                POP_JUMP_IF_FALSE        1 (to L7)

 175    L6:     RETURN_CONST             4 (False)

 177    L7:     LOAD_FAST                0 (f)
                LOAD_CONST               7 (10)
                BINARY_SUBSCR
                LOAD_CONST              14 (112)
                BINARY_OP               10 (-)
                LOAD_CONST              15 (1000)
                BINARY_OP                5 (*)
                LOAD_FAST                0 (f)
                LOAD_CONST              16 (11)
                BINARY_SUBSCR
                LOAD_CONST              17 (95)
                BINARY_OP               10 (-)
                BINARY_OP                0 (+)
                LOAD_CONST               3 (0)
                COMPARE_OP             119 (bool(!=))
                POP_JUMP_IF_FALSE        1 (to L9)

 178    L8:     RETURN_CONST             4 (False)

 180    L9:     LOAD_FAST                0 (f)
                LOAD_CONST              18 (14)
                BINARY_SUBSCR
                LOAD_FAST                0 (f)
                LOAD_CONST              16 (11)
                BINARY_SUBSCR
                BINARY_OP               10 (-)
                LOAD_CONST              11 (2)
                BINARY_OP                8 (**)
                LOAD_FAST                0 (f)
                LOAD_CONST              19 (19)
                BINARY_SUBSCR
                LOAD_FAST                0 (f)
                LOAD_CONST              16 (11)
                BINARY_SUBSCR
                BINARY_OP               10 (-)
                LOAD_CONST              11 (2)
                BINARY_OP                8 (**)
                BINARY_OP                0 (+)
                LOAD_FAST                0 (f)
                LOAD_CONST              20 (23)
                BINARY_SUBSCR
                LOAD_FAST                0 (f)
                LOAD_CONST              16 (11)
                BINARY_SUBSCR
                BINARY_OP               10 (-)
                LOAD_CONST              11 (2)
                BINARY_OP                8 (**)
                BINARY_OP                0 (+)

 181            LOAD_FAST                0 (f)
                LOAD_CONST              21 (26)
                BINARY_SUBSCR
                LOAD_FAST                0 (f)
                LOAD_CONST              16 (11)
                BINARY_SUBSCR
                BINARY_OP               10 (-)
                LOAD_CONST              11 (2)
                BINARY_OP                8 (**)

 180            BINARY_OP                0 (+)

 181            LOAD_FAST                0 (f)
                LOAD_CONST              22 (32)
                BINARY_SUBSCR
                LOAD_FAST                0 (f)
                LOAD_CONST              16 (11)
                BINARY_SUBSCR
                BINARY_OP               10 (-)
                LOAD_CONST              11 (2)
                BINARY_OP                8 (**)

 180            BINARY_OP                0 (+)
                STORE_FAST               1 (s11)

 182            LOAD_FAST                1 (s11)
                LOAD_CONST               3 (0)
                COMPARE_OP             119 (bool(!=))
                POP_JUMP_IF_FALSE        1 (to L11)

 183   L10:     RETURN_CONST             4 (False)

 185   L11:     LOAD_FAST                0 (f)
                LOAD_CONST              23 (12)
                BINARY_SUBSCR
                UNARY_INVERT
                LOAD_CONST               3 (0)
                BINARY_OP                0 (+)
                UNARY_INVERT
                LOAD_CONST              24 (49)
                BINARY_OP               10 (-)
                LOAD_CONST               3 (0)
                COMPARE_OP             119 (bool(!=))
                POP_JUMP_IF_FALSE        1 (to L13)

 186   L12:     RETURN_CONST             4 (False)

 187   L13:     LOAD_FAST                0 (f)
                LOAD_CONST              25 (33)
                BINARY_SUBSCR
                LOAD_FAST                0 (f)
                LOAD_CONST              23 (12)
                BINARY_SUBSCR
                BINARY_OP               10 (-)
                LOAD_CONST               3 (0)
                COMPARE_OP             119 (bool(!=))
                POP_JUMP_IF_FALSE        1 (to L15)

 188   L14:     RETURN_CONST             4 (False)

 190   L15:     LOAD_FAST                0 (f)
                LOAD_CONST              26 (13)
                BINARY_SUBSCR
                LOAD_CONST               7 (10)
                BINARY_OP                0 (+)
                LOAD_CONST              27 (5)
                BINARY_OP                5 (*)
                LOAD_CONST              17 (95)
                BINARY_OP               12 (^)
                LOAD_CONST              28 (553)
                COMPARE_OP             119 (bool(!=))
                POP_JUMP_IF_FALSE        1 (to L17)

 191   L16:     RETURN_CONST             4 (False)

 193   L17:     LOAD_FAST                0 (f)
                LOAD_CONST              29 (15)
                BINARY_SUBSCR
                LOAD_FAST                0 (f)
                LOAD_CONST              26 (13)
                BINARY_SUBSCR
                BINARY_OP               10 (-)
                LOAD_CONST              11 (2)
                BINARY_OP                8 (**)
                LOAD_FAST                0 (f)
                LOAD_CONST              30 (18)
                BINARY_SUBSCR
                LOAD_FAST                0 (f)
                LOAD_CONST              26 (13)
                BINARY_SUBSCR
                BINARY_OP               10 (-)
                LOAD_CONST              11 (2)
                BINARY_OP                8 (**)
                BINARY_OP                0 (+)
                LOAD_FAST                0 (f)
                LOAD_CONST              31 (34)
                BINARY_SUBSCR
                LOAD_FAST                0 (f)
                LOAD_CONST              26 (13)
                BINARY_SUBSCR
                BINARY_OP               10 (-)
                LOAD_CONST              11 (2)
                BINARY_OP                8 (**)
                BINARY_OP                0 (+)
                LOAD_CONST               3 (0)
                COMPARE_OP             119 (bool(!=))
                POP_JUMP_IF_FALSE        1 (to L19)

 194   L18:     RETURN_CONST             4 (False)

 196   L19:     RETURN_CONST            32 (True)

  --   L20:     PUSH_EXC_INFO

 197            LOAD_GLOBAL              0 (Exception)
                CHECK_EXC_MATCH
                POP_JUMP_IF_FALSE        3 (to L22)
                POP_TOP

 198   L21:     POP_EXCEPT
                RETURN_CONST             4 (False)

 197   L22:     RERAISE                  0

  --   L23:     COPY                     3
                POP_EXCEPT
                RERAISE                  1
ExceptionTable:
  L1 to L2 -> L20 [0]
  L3 to L4 -> L20 [0]
  L5 to L6 -> L20 [0]
  L7 to L8 -> L20 [0]
  L9 to L10 -> L20 [0]
  L11 to L12 -> L20 [0]
  L13 to L14 -> L20 [0]
  L15 to L16 -> L20 [0]
  L17 to L18 -> L20 [0]
  L20 to L21 -> L23 [1] lasti
  L22 to L23 -> L23 [1] lasti

Disassembly of <code object UU at 0x000002E07A864590, file "./OPz.py", line 201>:
 201            RESUME                   0

 202            NOP

 204    L1:     LOAD_FAST                0 (f)
                LOAD_CONST               1 (16)
                BINARY_SUBSCR
                LOAD_CONST               2 (2)
                BINARY_OP                5 (*)
                LOAD_CONST               3 (12)
                BINARY_OP               10 (-)
                LOAD_CONST               4 (196)
                BINARY_OP               10 (-)
                LOAD_CONST               5 (0)
                COMPARE_OP             119 (bool(!=))
                POP_JUMP_IF_FALSE        1 (to L3)

 205    L2:     RETURN_CONST             6 (False)

 207    L3:     LOAD_FAST                0 (f)
                LOAD_CONST               7 (17)
                BINARY_SUBSCR
                LOAD_CONST               5 (0)
                BINARY_OP                3 (<<)
                LOAD_CONST               5 (0)
                BINARY_OP               12 (^)
                LOAD_CONST               8 (52)
                COMPARE_OP             119 (bool(!=))
                POP_JUMP_IF_FALSE        1 (to L5)

 208    L4:     RETURN_CONST             6 (False)

 209    L5:     LOAD_FAST                0 (f)
                LOAD_CONST               9 (21)
                BINARY_SUBSCR
                LOAD_FAST                0 (f)
                LOAD_CONST               7 (17)
                BINARY_SUBSCR
                BINARY_OP               10 (-)
                LOAD_CONST               2 (2)
                BINARY_OP                8 (**)
                LOAD_FAST                0 (f)
                LOAD_CONST              10 (29)
                BINARY_SUBSCR
                LOAD_FAST                0 (f)
                LOAD_CONST               7 (17)
                BINARY_SUBSCR
                BINARY_OP               10 (-)
                LOAD_CONST               2 (2)
                BINARY_OP                8 (**)
                BINARY_OP                0 (+)
                LOAD_CONST               5 (0)
                COMPARE_OP             119 (bool(!=))
                POP_JUMP_IF_FALSE        1 (to L7)

 210    L6:     RETURN_CONST             6 (False)

 212    L7:     LOAD_FAST                0 (f)
                LOAD_CONST              11 (20)
                BINARY_SUBSCR
                LOAD_CONST              12 (3)
                BINARY_OP                5 (*)
                LOAD_CONST              13 (357)
                BINARY_OP               10 (-)
                LOAD_CONST               5 (0)
                COMPARE_OP             119 (bool(!=))
                POP_JUMP_IF_FALSE        1 (to L9)

 213    L8:     RETURN_CONST             6 (False)

 215    L9:     LOAD_FAST                0 (f)
                LOAD_CONST              14 (22)
                BINARY_SUBSCR
                LOAD_FAST                0 (f)
                LOAD_CONST              11 (20)
                BINARY_SUBSCR
                BINARY_OP               10 (-)
                LOAD_CONST               2 (2)
                BINARY_OP               10 (-)
                LOAD_CONST               5 (0)
                COMPARE_OP             119 (bool(!=))
                POP_JUMP_IF_FALSE        1 (to L11)

 216   L10:     RETURN_CONST             6 (False)

 218   L11:     LOAD_FAST                0 (f)
                LOAD_CONST              15 (24)
                BINARY_SUBSCR
                LOAD_CONST               5 (0)
                BINARY_OP               12 (^)
                LOAD_CONST              16 (48)
                BINARY_OP               10 (-)
                LOAD_CONST               5 (0)
                COMPARE_OP             119 (bool(!=))
                POP_JUMP_IF_FALSE        1 (to L13)

 219   L12:     RETURN_CONST             6 (False)

 221   L13:     LOAD_FAST                0 (f)
                LOAD_CONST              17 (25)
                BINARY_SUBSCR
                LOAD_FAST                0 (f)
                LOAD_CONST              14 (22)
                BINARY_SUBSCR
                LOAD_CONST              18 (7)
                BINARY_OP               10 (-)
                BINARY_OP               10 (-)
                LOAD_CONST               5 (0)
                COMPARE_OP             119 (bool(!=))
                POP_JUMP_IF_FALSE        1 (to L15)

 222   L14:     RETURN_CONST             6 (False)

 224   L15:     LOAD_FAST                0 (f)
                LOAD_CONST              19 (27)
                BINARY_SUBSCR
                LOAD_CONST              20 (76)
                BINARY_OP               10 (-)
                LOAD_FAST                0 (f)
                LOAD_CONST              21 (30)
                BINARY_SUBSCR
                LOAD_CONST              22 (118)
                BINARY_OP               10 (-)
                BINARY_OP                5 (*)
                LOAD_CONST               5 (0)
                COMPARE_OP             119 (bool(!=))
                POP_JUMP_IF_FALSE        1 (to L17)

 225   L16:     RETURN_CONST             6 (False)

 227   L17:     RETURN_CONST            23 (True)

  --   L18:     PUSH_EXC_INFO

 228            LOAD_GLOBAL              0 (Exception)
                CHECK_EXC_MATCH
                POP_JUMP_IF_FALSE        3 (to L20)
                POP_TOP

 229   L19:     POP_EXCEPT
                RETURN_CONST             6 (False)

 228   L20:     RERAISE                  0

  --   L21:     COPY                     3
                POP_EXCEPT
                RERAISE                  1
ExceptionTable:
  L1 to L2 -> L18 [0]
  L3 to L4 -> L18 [0]
  L5 to L6 -> L18 [0]
  L7 to L8 -> L18 [0]
  L9 to L10 -> L18 [0]
  L11 to L12 -> L18 [0]
  L13 to L14 -> L18 [0]
  L15 to L16 -> L18 [0]
  L18 to L19 -> L21 [1] lasti
  L20 to L21 -> L21 [1] lasti

Disassembly of <code object UUu at 0x000002E07A7EA9E0, file "./OPz.py", line 232>:
 232            RESUME                   0

 233            NOP

 234    L1:     LOAD_CONST               1 ('')
                LOAD_ATTR                1 (join + NULL|self)
                LOAD_CONST               2 (<code object <genexpr> at 0x000002E07A723030, file "./OPz.py", line 234>)
                MAKE_FUNCTION
                LOAD_FAST                0 (f)
                LOAD_CONST               3 (7)
                LOAD_CONST               4 (35)
                BINARY_SLICE
                GET_ITER
                CALL                     0
                CALL                     1
                STORE_FAST               1 (flag_content)

 235            LOAD_FAST                1 (flag_content)
                LOAD_CONST               0 (None)
                LOAD_CONST               5 (17)
                BINARY_SLICE
                STORE_FAST               2 (key_part)

 236            LOAD_GLOBAL              2 (hashlib)
                LOAD_ATTR                4 (sha256)
                PUSH_NULL
                LOAD_FAST                2 (key_part)
                LOAD_ATTR                7 (encode + NULL|self)
                CALL                     0
                CALL                     1
                LOAD_ATTR                9 (digest + NULL|self)
                CALL                     0
                STORE_FAST               3 (key)

 237            LOAD_FAST                1 (flag_content)
                LOAD_CONST               5 (17)
                LOAD_CONST               0 (None)
                BINARY_SLICE
                STORE_FAST               4 (plaintext)

 238            LOAD_GLOBAL             10 (base64)
                LOAD_ATTR               12 (b64decode)
                PUSH_NULL
                LOAD_CONST               6 ('jNtv1ielcDMRvnTLzB2hrg==')
                CALL                     1
                STORE_FAST               5 (expected_ciphertext)

 239            LOAD_CONST               7 (b'PWNSEC_CHALLENGE')
                STORE_FAST               6 (iv)

 240            LOAD_GLOBAL             14 (AES)
                LOAD_ATTR               16 (new)
                PUSH_NULL
                LOAD_FAST                3 (key)
                LOAD_GLOBAL             14 (AES)
                LOAD_ATTR               18 (MODE_CBC)
                LOAD_FAST                6 (iv)
                CALL                     3
                STORE_FAST               7 (cipher)

 241            LOAD_GLOBAL             21 (pad + NULL)
                LOAD_FAST                4 (plaintext)
                LOAD_ATTR                7 (encode + NULL|self)
                CALL                     0
                LOAD_GLOBAL             14 (AES)
                LOAD_ATTR               22 (block_size)
                CALL                     2
                STORE_FAST               8 (padded_plaintext)

 242            LOAD_FAST                7 (cipher)
                LOAD_ATTR               25 (encrypt + NULL|self)
                LOAD_FAST                8 (padded_plaintext)
                CALL                     1
                STORE_FAST               9 (ciphertext)

 243            LOAD_FAST_LOAD_FAST    149 (ciphertext, expected_ciphertext)
                COMPARE_OP             119 (bool(!=))
                POP_JUMP_IF_FALSE        1 (to L3)

 244    L2:     RETURN_CONST             8 (False)

 245    L3:     LOAD_GLOBAL             27 (sum + NULL)
                LOAD_FAST                0 (f)
                CALL                     1
                STORE_FAST              10 (total_sum)

 246            LOAD_GLOBAL             29 (print + NULL)
                LOAD_FAST               10 (total_sum)
                CALL                     1
                POP_TOP

 247            LOAD_FAST               10 (total_sum)
                LOAD_CONST               9 (3217)
                COMPARE_OP             119 (bool(!=))
                POP_JUMP_IF_FALSE        1 (to L5)

 248    L4:     RETURN_CONST             8 (False)

 247    L5:     NOP

 251            LOAD_FAST                0 (f)
                LOAD_CONST               4 (35)
                BINARY_SUBSCR
                LOAD_CONST              10 (125)
                COMPARE_OP              88 (bool(==))
                POP_JUMP_IF_TRUE         1 (to L6)
                RETURN_CONST             8 (False)

 252    L6:     RETURN_CONST            11 (True)

  --    L7:     PUSH_EXC_INFO

 249            LOAD_GLOBAL             30 (Exception)
                CHECK_EXC_MATCH
                POP_JUMP_IF_FALSE        3 (to L9)
                POP_TOP

 250    L8:     POP_EXCEPT
                RETURN_CONST             8 (False)

 249    L9:     RERAISE                  0

  --   L10:     COPY                     3
                POP_EXCEPT
                RERAISE                  1
ExceptionTable:
  L1 to L2 -> L7 [0]
  L3 to L4 -> L7 [0]
  L7 to L8 -> L10 [1] lasti
  L9 to L10 -> L10 [1] lasti

Disassembly of <code object <genexpr> at 0x000002E07A723030, file "./OPz.py", line 234>:
 234           RETURN_GENERATOR
               POP_TOP
       L1:     RESUME                   0
               LOAD_FAST                0 (.0)
               GET_ITER
       L2:     FOR_ITER                16 (to L3)
               STORE_FAST               1 (c)
               LOAD_GLOBAL              1 (chr + NULL)
               LOAD_FAST                1 (c)
               CALL                     1
               YIELD_VALUE              0
               RESUME                   5
               POP_TOP
               JUMP_BACKWARD           18 (to L2)
       L3:     END_FOR
               POP_TOP
               RETURN_CONST             0 (None)

  --   L4:     CALL_INTRINSIC_1         3 (INTRINSIC_STOPITERATION_ERROR)
               RERAISE                  1
ExceptionTable:
  L1 to L4 -> L4 [0] lasti

Disassembly of <code object you at 0x000002E07A502120, file "./OPz.py", line 254>:
 254            RESUME                   0

 255            LOAD_GLOBAL              1 (CALCSS + NULL)
                CALL                     0
                STORE_FAST               1 (dummy_result)

 256            LOAD_GLOBAL              3 (hash_function_1 + NULL)
                LOAD_FAST                1 (dummy_result)
                CALL                     1
                STORE_FAST               2 (_)

 257            LOAD_GLOBAL              5 (len + NULL)
                LOAD_FAST                0 (user_flag)
                CALL                     1
                LOAD_CONST               1 (36)
                COMPARE_OP             119 (bool(!=))
                POP_JUMP_IF_FALSE        1 (to L1)

 258            RETURN_CONST             2 (False)

 259    L1:     LOAD_FAST                0 (user_flag)
                GET_ITER
                LOAD_FAST_AND_CLEAR      3 (c)
                SWAP                     2
        L2:     BUILD_LIST               0
                SWAP                     2
                GET_ITER
        L3:     FOR_ITER                14 (to L4)
                STORE_FAST               3 (c)
                LOAD_GLOBAL              7 (ord + NULL)
                LOAD_FAST                3 (c)
                CALL                     1
                LIST_APPEND              2
                JUMP_BACKWARD           16 (to L3)
        L4:     END_FOR
                POP_TOP
        L5:     STORE_FAST               4 (f)
                STORE_FAST               3 (c)

 260            NOP

 261    L6:     LOAD_GLOBAL              9 (Uu + NULL)
                LOAD_FAST                4 (f)
                CALL                     1
                TO_BOOL
                POP_JUMP_IF_TRUE         1 (to L8)
        L7:     RETURN_CONST             2 (False)

 262    L8:     LOAD_GLOBAL             11 (uU + NULL)
                LOAD_FAST                4 (f)
                CALL                     1
                TO_BOOL
                POP_JUMP_IF_TRUE         1 (to L10)
        L9:     RETURN_CONST             2 (False)

 263   L10:     LOAD_GLOBAL             13 (UU + NULL)
                LOAD_FAST                4 (f)
                CALL                     1
                TO_BOOL
                POP_JUMP_IF_TRUE         1 (to L12)
       L11:     RETURN_CONST             2 (False)

 264   L12:     LOAD_GLOBAL             15 (UUu + NULL)
                LOAD_FAST                4 (f)
                CALL                     1
                TO_BOOL
                POP_JUMP_IF_TRUE         1 (to L14)
       L13:     RETURN_CONST             2 (False)

 265   L14:     RETURN_CONST             3 (True)

  --   L15:     SWAP                     2
                POP_TOP

 259            SWAP                     2
                STORE_FAST               3 (c)
                RERAISE                  0

  --   L16:     PUSH_EXC_INFO

 266            POP_TOP

 267   L17:     POP_EXCEPT
                RETURN_CONST             2 (False)

  --   L18:     COPY                     3
                POP_EXCEPT
                RERAISE                  1
ExceptionTable:
  L2 to L5 -> L15 [2]
  L6 to L7 -> L16 [0]
  L8 to L9 -> L16 [0]
  L10 to L11 -> L16 [0]
  L12 to L13 -> L16 [0]
  L16 to L17 -> L18 [1] lasti

Disassembly of <code object intenTIONAL_FUNCS at 0x000002E07A756E50, file "./OPz.py", line 269>:
269           RESUME                   0

270           LOAD_CONST               1 (<code object nested_dummy_1 at 0x000002E07A72A790, file "./OPz.py", line 270>)
              MAKE_FUNCTION
              STORE_FAST               0 (nested_dummy_1)

277           LOAD_CONST               2 (<code object nested_dummy_2 at 0x000002E07A541E90, file "./OPz.py", line 277>)
              MAKE_FUNCTION
              STORE_FAST               1 (nested_dummy_2)

288           LOAD_CONST               3 (<code object nested_dummy_3 at 0x000002E07A4BB230, file "./OPz.py", line 288>)
              MAKE_FUNCTION
              STORE_FAST               2 (nested_dummy_3)

306           LOAD_FAST                0 (nested_dummy_1)
              PUSH_NULL
              CALL                     0
              LOAD_FAST                1 (nested_dummy_2)
              PUSH_NULL
              CALL                     0
              LOAD_FAST                2 (nested_dummy_3)
              PUSH_NULL
              CALL                     0
              BUILD_LIST               3
              STORE_FAST               3 (results)

307           LOAD_GLOBAL              1 (sum + NULL)
              LOAD_FAST                3 (results)
              CALL                     1
              LOAD_CONST               4 (1000000)
              BINARY_OP                6 (%)
              RETURN_VALUE

Disassembly of <code object nested_dummy_1 at 0x000002E07A72A790, file "./OPz.py", line 270>:
270           RESUME                   0

271           LOAD_CONST               1 (<code object inner_dummy_1 at 0x000002E07A72A880, file "./OPz.py", line 271>)
              MAKE_FUNCTION
              STORE_FAST               0 (inner_dummy_1)

275           LOAD_FAST                0 (inner_dummy_1)
              PUSH_NULL
              CALL                     0
              LOAD_CONST               2 (42)
              BINARY_OP                0 (+)
              RETURN_VALUE

Disassembly of <code object inner_dummy_1 at 0x000002E07A72A880, file "./OPz.py", line 271>:
271           RESUME                   0

272           LOAD_CONST               1 (<code object deep_dummy_1 at 0x000002E07A793E30, file "./OPz.py", line 272>)
              MAKE_FUNCTION
              STORE_FAST               0 (deep_dummy_1)

274           LOAD_FAST                0 (deep_dummy_1)
              PUSH_NULL
              CALL                     0
              LOAD_CONST               2 (2)
              BINARY_OP                5 (*)
              RETURN_VALUE

Disassembly of <code object deep_dummy_1 at 0x000002E07A793E30, file "./OPz.py", line 272>:
272           RESUME                   0

273           LOAD_GLOBAL              1 (sum + NULL)
              LOAD_CONST               1 (<code object <genexpr> at 0x000002E07A723830, file "./OPz.py", line 273>)
              MAKE_FUNCTION
              LOAD_GLOBAL              3 (range + NULL)
              LOAD_CONST               2 (100)
              CALL                     1
              GET_ITER
              CALL                     0
              CALL                     1
              RETURN_VALUE

Disassembly of <code object <genexpr> at 0x000002E07A723830, file "./OPz.py", line 273>:
 273           RETURN_GENERATOR
               POP_TOP
       L1:     RESUME                   0
               LOAD_FAST                0 (.0)
               GET_ITER
       L2:     FOR_ITER                 9 (to L3)
               STORE_FAST_LOAD_FAST    17 (i, i)
               LOAD_CONST               0 (2)
               BINARY_OP                8 (**)
               YIELD_VALUE              0
               RESUME                   5
               POP_TOP
               JUMP_BACKWARD           11 (to L2)
       L3:     END_FOR
               POP_TOP
               RETURN_CONST             1 (None)

  --   L4:     CALL_INTRINSIC_1         3 (INTRINSIC_STOPITERATION_ERROR)
               RERAISE                  1
ExceptionTable:
  L1 to L4 -> L4 [0] lasti

Disassembly of <code object nested_dummy_2 at 0x000002E07A541E90, file "./OPz.py", line 277>:
277           RESUME                   0

278           BUILD_MAP                0
              STORE_FAST               0 (data)

279           LOAD_GLOBAL              1 (range + NULL)
              LOAD_CONST               1 (500)
              CALL                     1
              GET_ITER
      L1:     FOR_ITER                82 (to L2)
              STORE_FAST               1 (i)

281           LOAD_FAST                1 (i)
              LOAD_CONST               2 (2)
              BINARY_OP                5 (*)

282           LOAD_FAST                1 (i)
              LOAD_CONST               2 (2)
              BINARY_OP                8 (**)

283           LOAD_FAST                1 (i)
              LOAD_CONST               3 (3)
              BINARY_OP                8 (**)

284           LOAD_GLOBAL              2 (hashlib)
              LOAD_ATTR                4 (md5)
              PUSH_NULL
              LOAD_GLOBAL              7 (str + NULL)
              LOAD_FAST                1 (i)
              CALL                     1
              LOAD_ATTR                9 (encode + NULL|self)
              CALL                     0
              CALL                     1
              LOAD_ATTR               11 (hexdigest + NULL|self)
              CALL                     0

280           LOAD_CONST               4 (('value', 'square', 'cube', 'hash'))
              BUILD_CONST_KEY_MAP      4
              LOAD_FAST                0 (data)
              LOAD_CONST               5 ('key_')
              LOAD_FAST                1 (i)
              FORMAT_SIMPLE
              BUILD_STRING             2
              STORE_SUBSCR
              JUMP_BACKWARD           84 (to L1)

279   L2:     END_FOR
              POP_TOP

286           LOAD_GLOBAL             13 (len + NULL)
              LOAD_FAST                0 (data)
              CALL                     1
              RETURN_VALUE

Disassembly of <code object nested_dummy_3 at 0x000002E07A4BB230, file "./OPz.py", line 288>:
288           RESUME                   0

289           BUILD_LIST               0
              STORE_FAST               0 (matrix)

290           LOAD_GLOBAL              1 (range + NULL)
              LOAD_CONST               1 (30)
              CALL                     1
              GET_ITER
      L1:     FOR_ITER               102 (to L6)
              STORE_FAST               1 (i)

291           BUILD_LIST               0
              STORE_FAST               2 (row)

292           LOAD_GLOBAL              1 (range + NULL)
              LOAD_CONST               1 (30)
              CALL                     1
              GET_ITER
      L2:     FOR_ITER                65 (to L5)
              STORE_FAST               3 (j)

293           LOAD_FAST_LOAD_FAST     19 (i, j)
              BINARY_OP                5 (*)
              LOAD_FAST                1 (i)
              BINARY_OP                0 (+)
              LOAD_FAST                3 (j)
              BINARY_OP                0 (+)
              LOAD_CONST               2 (256)
              BINARY_OP                6 (%)
              STORE_FAST               4 (val)

294           LOAD_FAST                4 (val)
              LOAD_CONST               3 (2)
              BINARY_OP                6 (%)
              LOAD_CONST               4 (0)
              COMPARE_OP              88 (bool(==))
              POP_JUMP_IF_FALSE       12 (to L3)

295           LOAD_FAST                4 (val)
              LOAD_CONST               5 (3)
              BINARY_OP                5 (*)
              LOAD_CONST               6 (7)
              BINARY_OP                0 (+)
              LOAD_CONST               7 (128)
              BINARY_OP                6 (%)
              STORE_FAST               4 (val)
              JUMP_FORWARD            11 (to L4)

297   L3:     LOAD_FAST                4 (val)
              LOAD_CONST               8 (11)
              BINARY_OP                0 (+)
              LOAD_CONST               3 (2)
              BINARY_OP                5 (*)
              LOAD_CONST               2 (256)
              BINARY_OP                6 (%)
              STORE_FAST               4 (val)

298   L4:     LOAD_FAST                2 (row)
              LOAD_ATTR                3 (append + NULL|self)
              LOAD_FAST                4 (val)
              CALL                     1
              POP_TOP
              JUMP_BACKWARD           67 (to L2)

292   L5:     END_FOR
              POP_TOP

299           LOAD_FAST                0 (matrix)
              LOAD_ATTR                3 (append + NULL|self)
              LOAD_FAST                2 (row)
              CALL                     1
              POP_TOP
              JUMP_BACKWARD          104 (to L1)

290   L6:     END_FOR
              POP_TOP

300           LOAD_CONST               4 (0)
              STORE_FAST               5 (result)

301           LOAD_FAST                0 (matrix)
              GET_ITER
      L7:     FOR_ITER                22 (to L8)
              STORE_FAST               2 (row)

302           LOAD_FAST                5 (result)
              LOAD_GLOBAL              5 (sum + NULL)
              LOAD_FAST                2 (row)
              CALL                     1
              BINARY_OP               13 (+=)
              STORE_FAST               5 (result)

303           LOAD_FAST                5 (result)
              LOAD_CONST               9 (999983)
              BINARY_OP                6 (%)
              STORE_FAST               5 (result)
              JUMP_BACKWARD           24 (to L7)

301   L8:     END_FOR
              POP_TOP

304           LOAD_FAST                5 (result)
              RETURN_VALUE

Disassembly of <code object Dd at 0x000002E07A898D90, file "./OPz.py", line 318>:
318            RESUME                   0

319            LOAD_CONST               1 (0)
               STORE_FAST               0 (result)

320            LOAD_GLOBAL              0 (MEGA_DUMMY_DATA)
               LOAD_ATTR                3 (items + NULL|self)
               CALL                     0
               GET_ITER
       L1:     FOR_ITER               156 (to L8)
               UNPACK_SEQUENCE          2
               STORE_FAST_STORE_FAST   18 (key, value)

321            LOAD_GLOBAL              5 (isinstance + NULL)
               LOAD_FAST                2 (value)
               LOAD_GLOBAL              6 (list)
               CALL                     2
               TO_BOOL
               POP_JUMP_IF_TRUE         2 (to L2)
               JUMP_BACKWARD           28 (to L1)

322    L2:     LOAD_FAST                2 (value)
               LOAD_CONST               0 (None)
               LOAD_CONST               2 (10)
               BINARY_SLICE
               GET_ITER
       L3:     FOR_ITER               119 (to L7)
               STORE_FAST               3 (item)

323            LOAD_GLOBAL              5 (isinstance + NULL)
               LOAD_FAST                3 (item)
               LOAD_GLOBAL              8 (int)
               LOAD_GLOBAL             10 (float)
               BUILD_TUPLE              2
               CALL                     2
               TO_BOOL
               POP_JUMP_IF_FALSE        9 (to L4)

324            LOAD_FAST_LOAD_FAST      3 (result, item)
               LOAD_CONST               3 (1000)
               BINARY_OP                6 (%)
               BINARY_OP               13 (+=)
               STORE_FAST               0 (result)
               JUMP_BACKWARD           39 (to L3)

325    L4:     LOAD_GLOBAL              5 (isinstance + NULL)
               LOAD_FAST                3 (item)
               LOAD_GLOBAL             12 (str)
               CALL                     2
               TO_BOOL
               POP_JUMP_IF_FALSE       19 (to L5)

326            LOAD_FAST                0 (result)
               LOAD_GLOBAL             15 (len + NULL)
               LOAD_FAST                3 (item)
               CALL                     1
               LOAD_CONST               4 (100)
               BINARY_OP                6 (%)
               BINARY_OP               13 (+=)
               STORE_FAST               0 (result)
               JUMP_BACKWARD           79 (to L3)

327    L5:     LOAD_GLOBAL              5 (isinstance + NULL)
               LOAD_FAST                3 (item)
               LOAD_GLOBAL             16 (dict)
               CALL                     2
               TO_BOOL
               POP_JUMP_IF_TRUE         2 (to L6)
               JUMP_BACKWARD          102 (to L3)

328    L6:     LOAD_FAST                0 (result)
               LOAD_GLOBAL             15 (len + NULL)
               LOAD_FAST                3 (item)
               CALL                     1
               LOAD_CONST               5 (50)
               BINARY_OP                6 (%)
               BINARY_OP               13 (+=)
               STORE_FAST               0 (result)
               JUMP_BACKWARD          121 (to L3)

322    L7:     END_FOR
               POP_TOP
               JUMP_BACKWARD          158 (to L1)

320    L8:     END_FOR
               POP_TOP

329            LOAD_GLOBAL             19 (sum + NULL)
               LOAD_CONST               6 (<code object <genexpr> at 0x000002E07A741570, file "./OPz.py", line 329>)
               MAKE_FUNCTION
               LOAD_GLOBAL             21 (range + NULL)
               LOAD_CONST               3 (1000)
               CALL                     1
               GET_ITER
               CALL                     0
               CALL                     1
               STORE_FAST               4 (fibonacci_sum)

330            LOAD_CONST               7 (1)
               STORE_FAST               5 (prime_product)

331            LOAD_CONST               8 ((2, 3, 5, 7, 11, 13, 17, 19, 23, 29))
               GET_ITER
       L9:     FOR_ITER                12 (to L10)
               STORE_FAST               6 (p)

332            LOAD_FAST_LOAD_FAST     86 (prime_product, p)
               BINARY_OP               18 (*=)
               STORE_FAST               5 (prime_product)

333            LOAD_FAST                5 (prime_product)
               LOAD_CONST               9 (999983)
               BINARY_OP                6 (%)
               STORE_FAST               5 (prime_product)
               JUMP_BACKWARD           14 (to L9)

331   L10:     END_FOR
               POP_TOP

334            LOAD_FAST_LOAD_FAST      4 (result, fibonacci_sum)
               BINARY_OP                0 (+)
               LOAD_FAST                5 (prime_product)
               BINARY_OP                0 (+)
               LOAD_CONST              10 (999999999)
               BINARY_OP                6 (%)
               RETURN_VALUE

Disassembly of <code object <genexpr> at 0x000002E07A741570, file "./OPz.py", line 329>:
 329           RETURN_GENERATOR
               POP_TOP
       L1:     RESUME                   0
               LOAD_FAST                0 (.0)
               GET_ITER
       L2:     FOR_ITER                17 (to L5)
               STORE_FAST_LOAD_FAST    17 (i, i)
               LOAD_CONST               0 (13)
               BINARY_OP                6 (%)
               LOAD_CONST               1 (0)
               COMPARE_OP              88 (bool(==))
       L3:     POP_JUMP_IF_TRUE         2 (to L4)
               JUMP_BACKWARD           13 (to L2)
       L4:     LOAD_FAST                1 (i)
               YIELD_VALUE              0
               RESUME                   5
               POP_TOP
               JUMP_BACKWARD           19 (to L2)
       L5:     END_FOR
               POP_TOP
               RETURN_CONST             2 (None)

  --   L6:     CALL_INTRINSIC_1         3 (INTRINSIC_STOPITERATION_ERROR)
               RERAISE                  1
ExceptionTable:
  L1 to L3 -> L6 [0] lasti
  L4 to L6 -> L6 [0] lasti
