Compiled from "Main.jasm"
public class Main {
  public static void main(java.lang.String[]);
    Code:
       0: getstatic     #13                 // Field java/lang/System.out:Ljava/io/PrintStream;
       3: ldc           #15                 // String \n\n==================================================\nwelcome to the bear flag calculator!\ncalculating your flag... please be patient...\nyour flag is:
       5: invokevirtual #21                 // Method java/io/PrintStream.print:(Ljava/lang/String;)V
       8: ldc           #22                 // int 0
      10: ldc           #23                 // int 33
      12: istore_0
      13: ldc2_w        #24                 // long 139968l
      16: ldc2_w        #26                 // long 5668704l
      19: ldc2_w        #28                 // long -1304525088l
      22: ldc2_w        #30                 // long -136713343536l
      25: ldc2_w        #32                 // long -6199669846548l
      28: ldc2_w        #34                 // long -168942465814554l
      31: ldc2_w        #36                 // long -3090696072809988l
      34: ldc2_w        #38                 // long -40091725176298332l
      37: ldc2_w        #40                 // long -380192091498886956l
      40: ldc2_w        #42                 // long -2681484757726506270l
      43: ldc2_w        #44                 // long 4262732026354931284l
      46: ldc2_w        #46                 // long -1010288408357244504l
      49: ldc2_w        #48                 // long -1290340284545482380l
      52: ldc2_w        #50                 // long 2078316189846199370l
      55: ldc2_w        #52                 // long 8600033438064957380l
      58: ldc2_w        #54                 // long 1420642205836072100l
      61: ldc2_w        #56                 // long -8455265360534582900l
      64: ldc2_w        #58                 // long 1665170620416952526l
      67: ldc2_w        #60                 // long -1301775785128209268l
      70: iload_0
      71: iconst_1
      72: isub
      73: dup
      74: istore_0
      75: ifgt          13
      78: ldc           #62                 // int 19
      80: ldc           #23                 // int 33
      82: istore_0
      83: ldc2_w        #63                 // long 8748l
      86: ldc2_w        #65                 // long 1414260l
      89: ldc2_w        #67                 // long 26723439l
      92: ldc2_w        #69                 // long -10660294170l
      95: ldc2_w        #71                 // long -1221377280201l
      98: ldc2_w        #73                 // long -69067032564330l
     101: ldc2_w        #75                 // long -2484601406995677l
     104: ldc2_w        #77                 // long -61766129802830370l
     107: ldc2_w        #79                 // long -1102152172282805925l
     110: ldc2_w        #81                 // long 4064385248137766326l
     113: ldc2_w        #83                 // long -9180640905693487451l
     116: ldc2_w        #85                 // long -2428929420931013902l
     119: ldc2_w        #87                 // long 7433817110216891877l
     122: ldc2_w        #89                 // long 570301496243907042l
     125: ldc2_w        #91                 // long 5254839426900975617l
     128: ldc2_w        #93                 // long -1280151659966208822l
     131: ldc2_w        #95                 // long -8888534056241547107l
     134: ldc2_w        #97                 // long 3270166363338602206l
     137: ldc2_w        #99                 // long -7827650834523256696l
     140: iload_0
     141: iconst_1
     142: isub
     143: dup
     144: istore_0
     145: ifgt          83
     148: ldc           #62                 // int 19
     150: ldc           #23                 // int 33
     152: istore_0
     153: ldc2_w        #101                // long 576l
     156: ldc2_w        #103                // long 146496l
     159: ldc2_w        #105                // long 12112048l
     162: ldc2_w        #107                // long -275935968l
     165: ldc2_w        #109                // long -147400189732l
     168: ldc2_w        #111                // long -15435698167996l
     171: ldc2_w        #113                // long -963396145601043l
     174: ldc2_w        #115                // long -41855620854074132l
     177: ldc2_w        #117                // long -1341408083771387994l
     180: ldc2_w        #119                // long 4312977838210654592l
     183: ldc2_w        #121                // long 1791641609139274227l
     186: ldc2_w        #123                // long -3503117117902889960l
     189: ldc2_w        #125                // long -3088454007629645152l
     192: ldc2_w        #127                // long 8848217138088398820l
     195: ldc2_w        #129                // long 3062279033678910147l
     198: ldc2_w        #131                // long -6684007589624798244l
     201: ldc2_w        #133                // long 4740777470248945982l
     204: ldc2_w        #135                // long 9040021092677972248l
     207: ldc2_w        #137                // long 3652210279687931405l
     210: iload_0
     211: iconst_1
     212: isub
     213: dup
     214: istore_0
     215: ifgt          153
     218: ldc           #62                 // int 19
     220: ldc           #23                 // int 33
     222: istore_0
     223: ldc2_w        #139                // long 46656l
     226: ldc2_w        #141                // long 6788448l
     229: ldc2_w        #143                // long 39481344l
     232: ldc2_w        #145                // long -58856964336l
     235: ldc2_w        #147                // long -6103475822700l
     238: ldc2_w        #149                // long -332663882200458l
     241: ldc2_w        #151                // long -11846817654688062l
     244: ldc2_w        #153                // long -297391697652357612l
     247: ldc2_w        #155                // long -5448907467944869656l
     250: ldc2_w        #157                // long -240756732184936670l
     253: ldc2_w        #159                // long 7557340208061021758l
     256: ldc2_w        #161                // long -3055365093473528504l
     259: ldc2_w        #163                // long 862558048250048660l
     262: ldc2_w        #165                // long 8515228054694805722l
     265: ldc2_w        #167                // long -7642578819372557762l
     268: ldc2_w        #169                // long -3454788906313965484l
     271: ldc2_w        #171                // long -4477929424018395536l
     274: ldc2_w        #173                // long 2988288913377215854l
     277: ldc2_w        #175                // long -4830491881878959358l
     280: iload_0
     281: iconst_1
     282: isub
     283: dup
     284: istore_0
     285: ifgt          223
     288: ldc           #62                 // int 19
     290: ldc           #23                 // int 33
     292: istore_0
     293: ldc2_w        #177                // long 34992l
     296: ldc2_w        #179                // long 5015520l
     299: ldc2_w        #181                // long 102054168l
     302: ldc2_w        #183                // long -29631948768l
     305: ldc2_w        #185                // long -3372424301925l
     308: ldc2_w        #187                // long -192396619525590l
     311: ldc2_w        #189                // long -7195231516974519l
     314: ldc2_w        #191                // long -192191118265946044l
     317: ldc2_w        #193                // long -3814454414305521069l
     320: ldc2_w        #195                // long -2039952563681889898l
     323: ldc2_w        #197                // long 4210575270153678009l
     326: ldc2_w        #199                // long 6197086543140623960l
     329: ldc2_w        #201                // long -8480945980504676871l
     332: ldc2_w        #203                // long -2409180279491630794l
     335: ldc2_w        #205                // long -2611622199478744541l
     338: ldc2_w        #207                // long -4246470620712608252l
     341: ldc2_w        #209                // long 1457600041085969513l
     344: ldc2_w        #211                // long 727591600248688234l
     347: ldc2_w        #213                // long 4873507416256484803l
     350: iload_0
     351: iconst_1
     352: isub
     353: dup
     354: istore_0
     355: ifgt          293
     358: ldc           #62                 // int 19
     360: ldc           #23                 // int 33
     362: istore_0
     363: ldc2_w        #177                // long 34992l
     366: ldc2_w        #215                // long 2437776l
     369: ldc2_w        #217                // long -136554336l
     372: ldc2_w        #219                // long -22142284740l
     375: ldc2_w        #221                // long -1155643517547l
     378: ldc2_w        #223                // long -34440854121072l
     381: ldc2_w        #225                // long -671061906273642l
     384: ldc2_w        #227                // long -9077406493695852l
     387: ldc2_w        #229                // long -88058569837809285l
     390: ldc2_w        #231                // long -623934430871284104l
     393: ldc2_w        #233                // long -3258622023335906448l
     396: ldc2_w        #235                // long 5876162155016540260l
     399: ldc2_w        #237                // long 1231306228709245595l
     402: ldc2_w        #239                // long 222499297403274784l
     405: ldc2_w        #241                // long 2569385785572497022l
     408: ldc2_w        #243                // long 1310833369215277644l
     411: ldc2_w        #245                // long 2010343674646223941l
     414: ldc2_w        #247                // long -8821384138009525304l
     417: ldc2_w        #249                // long -4508618494801320900l
     420: iload_0
     421: iconst_1
     422: isub
     423: dup
     424: istore_0
     425: ifgt          363
     428: ldc           #62                 // int 19
     430: ldc           #23                 // int 33
     432: istore_0
     433: ldc2_w        #251                // long 1679616l
     436: ldc2_w        #253                // long 277136640l
     439: ldc2_w        #255                // long 9692970624l
     442: ldc2_w        #257                // long -1422224101440l
     445: ldc2_w        #259                // long -204338969339904l
     448: ldc2_w        #261                // long -13478104966543920l
     451: ldc2_w        #263                // long -574707629113712856l
     454: ldc2_w        #265                // long 1007863641486612436l
     457: ldc2_w        #267                // long -5197709306964673473l
     460: ldc2_w        #269                // long -8387002613302458838l
     463: ldc2_w        #271                // long -8206330036474289953l
     466: ldc2_w        #273                // long 4013747348815460624l
     469: ldc2_w        #275                // long 3274496121279401134l
     472: ldc2_w        #277                // long -5313291341872763108l
     475: ldc2_w        #279                // long 3620609337395217774l
     478: ldc2_w        #281                // long -9025275002787940948l
     481: ldc2_w        #283                // long -1220755215152531853l
     484: ldc2_w        #285                // long -4109684211436336742l
     487: ldc2_w        #287                // long 4924223426003895211l
     490: iload_0
     491: iconst_1
     492: isub
     493: dup
     494: istore_0
     495: ifgt          433
     498: ldc           #62                 // int 19
     500: ldc           #23                 // int 33
     502: istore_0
     503: ldc2_w        #289                // long 5184l
     506: ldc2_w        #291                // long 884736l
     509: ldc2_w        #293                // long 23056272l
     512: ldc2_w        #295                // long -6824846400l
     515: ldc2_w        #297                // long -914899457860l
     518: ldc2_w        #299                // long -60350940043552l
     521: ldc2_w        #301                // long -2583666692190413l
     524: ldc2_w        #303                // long -78260436991300276l
     527: ldc2_w        #305                // long -1743625496459165555l
     530: ldc2_w        #307                // long 7787189488059442192l
     533: ldc2_w        #309                // long 2477390998100830586l
     536: ldc2_w        #311                // long -4650455043496741848l
     539: ldc2_w        #313                // long -8303729601757835578l
     542: ldc2_w        #315                // long 7484218889437802576l
     545: ldc2_w        #317                // long 2936373258989651239l
     548: ldc2_w        #319                // long 3169085310323819692l
     551: ldc2_w        #321                // long 1300550019928774049l
     554: ldc2_w        #323                // long 386990088051114720l
     557: ldc2_w        #325                // long -8896528384153874260l
     560: iload_0
     561: iconst_1
     562: isub
     563: dup
     564: istore_0
     565: ifgt          503
     568: ldc           #62                 // int 19
     570: ldc           #23                 // int 33
     572: istore_0
     573: ldc2_w        #327                // long 104976l
     576: ldc2_w        #329                // long 25876584l
     579: ldc2_w        #331                // long 2207064996l
     582: ldc2_w        #333                // long -1421067402l
     585: ldc2_w        #335                // long -16975173429054l
     588: ldc2_w        #337                // long -1787546503915218l
     591: ldc2_w        #339                // long -107028057723819894l
     594: ldc2_w        #341                // long -4405879701728549154l
     597: ldc2_w        #343                // long -4038252538400293702l
     600: ldc2_w        #345                // long -921567798844201370l
     603: ldc2_w        #347                // long 3047470220774532874l
     606: ldc2_w        #349                // long 1443679329959270978l
     609: ldc2_w        #351                // long -727597003368712666l
     612: ldc2_w        #353                // long 4788714558851661930l
     615: ldc2_w        #355                // long -181319753990644770l
     618: ldc2_w        #357                // long 3270964186097359338l
     621: ldc2_w        #359                // long 3404651935777878478l
     624: ldc2_w        #361                // long -6769392680452861670l
     627: ldc2_w        #363                // long -3993177484119107222l
     630: iload_0
     631: iconst_1
     632: isub
     633: dup
     634: istore_0
     635: ifgt          573
     638: ldc           #62                 // int 19
     640: ldc           #23                 // int 33
     642: istore_0
     643: ldc2_w        #365                // long 10368l
     646: ldc2_w        #367                // long 2401920l
     649: ldc2_w        #369                // long 183307104l
     652: ldc2_w        #371                // long -2406889536l
     655: ldc2_w        #373                // long -1548736359688l
     658: ldc2_w        #375                // long -142728231469336l
     661: ldc2_w        #377                // long -7618121483991942l
     664: ldc2_w        #379                // long -277207393691124592l
     667: ldc2_w        #381                // long -7286275161642921244l
     670: ldc2_w        #383                // long 5728269050213558216l
     673: ldc2_w        #385                // long 2163257914477573294l
     676: ldc2_w        #387                // long -1651253694791623968l
     679: ldc2_w        #389                // long -5332672475574895888l
     682: ldc2_w        #391                // long 5670581969580992184l
     685: ldc2_w        #393                // long 4722922663732830262l
     688: ldc2_w        #395                // long -5140488267151724464l
     691: ldc2_w        #397                // long 2857217307181004404l
     694: ldc2_w        #399                // long 3689631063985650840l
     697: ldc2_w        #401                // long -7544184654336337022l
     700: iload_0
     701: iconst_1
     702: isub
     703: dup
     704: istore_0
     705: ifgt          643
     708: ldc           #62                 // int 19
     710: ldc           #23                 // int 33
     712: istore_0
     713: ldc2_w        #139                // long 46656l
     716: ldc2_w        #403                // long 4385664l
     719: ldc2_w        #405                // long -201003120l
     722: ldc2_w        #407                // long -53814639168l
     725: ldc2_w        #409                // long -4013457016212l
     728: ldc2_w        #411                // long -173617432839240l
     731: ldc2_w        #413                // long -5042862562373013l
     734: ldc2_w        #415                // long -104488640651251224l
     737: ldc2_w        #417                // long -1591746789722905338l
     740: ldc2_w        #419                // long 354495864531750664l
     743: ldc2_w        #421                // long -6599072343152943871l
     746: ldc2_w        #423                // long -4411242035675151760l
     749: ldc2_w        #425                // long 40341593311307744l
     752: ldc2_w        #427                // long 5319299384879524584l
     755: ldc2_w        #429                // long 2112449841113457213l
     758: ldc2_w        #431                // long 361235905345368744l
     761: ldc2_w        #433                // long 4874699891546192526l
     764: ldc2_w        #435                // long -6481032793851284968l
     767: ldc2_w        #437                // long -3793531303538899289l
     770: iload_0
     771: iconst_1
     772: isub
     773: dup
     774: istore_0
     775: ifgt          713
     778: ldc           #62                 // int 19
     780: ldc           #23                 // int 33
     782: istore_0
     783: ldc2_w        #439                // long 15552l
     786: ldc2_w        #441                // long 4183488l
     789: ldc2_w        #443                // long 373073904l
     792: ldc2_w        #445                // long -4329354672l
     795: ldc2_w        #447                // long -3953354662764l
     798: ldc2_w        #449                // long -422427961750700l
     801: ldc2_w        #451                // long -26010393342733715l
     804: ldc2_w        #453                // long -1093860902509714309l
     807: ldc2_w        #455                // long 3490423937368633287l
     810: ldc2_w        #457                // long -5464188247457000747l
     813: ldc2_w        #459                // long -3681525459521522362l
     816: ldc2_w        #461                // long 5370563176357251742l
     819: ldc2_w        #463                // long -800638681479098462l
     822: ldc2_w        #465                // long 4585505281331689694l
     825: ldc2_w        #467                // long 706712822569378793l
     828: ldc2_w        #469                // long -7236641882254413177l
     831: ldc2_w        #471                // long 2632951496217652339l
     834: ldc2_w        #473                // long -3704181124037433527l
     837: ldc2_w        #475                // long 825596779461060420l
     840: iload_0
     841: iconst_1
     842: isub
     843: dup
     844: istore_0
     845: ifgt          783
     848: ldc           #62                 // int 19
     850: ldc           #23                 // int 33
     852: istore_0
     853: ldc2_w        #477                // long 78732l
     856: ldc2_w        #479                // long 6928416l
     859: ldc2_w        #481                // long -227358333l
     862: ldc2_w        #483                // long -58603762521l
     865: ldc2_w        #485                // long -3712208766255l
     868: ldc2_w        #487                // long -132333403855653l
     871: ldc2_w        #489                // long -3102068925468351l
     874: ldc2_w        #491                // long -51060111466457637l
     877: ldc2_w        #493                // long -610981839411598827l
     880: ldc2_w        #495                // long -5419154092790447537l
     883: ldc2_w        #497                // long 909882275855010683l
     886: ldc2_w        #499                // long 5100093266219088197l
     889: ldc2_w        #501                // long -4593515856727495933l
     892: ldc2_w        #503                // long 376691970646840769l
     895: ldc2_w        #505                // long -246464679650945717l
     898: ldc2_w        #507                // long 5733858527181028217l
     901: ldc2_w        #509                // long 3120592970343724235l
     904: ldc2_w        #511                // long 7401133743249552309l
     907: ldc2_w        #513                // long -6503471003769017290l
     910: iload_0
     911: iconst_1
     912: isub
     913: dup
     914: istore_0
     915: ifgt          853
     918: ldc           #62                 // int 19
     920: ldc           #23                 // int 33
     922: istore_0
     923: ldc2_w        #515                // long 2592l
     926: ldc2_w        #517                // long 629856l
     929: ldc2_w        #519                // long 44302320l
     932: ldc2_w        #521                // long -2073761280l
     935: ldc2_w        #523                // long -581570685934l
     938: ldc2_w        #525                // long -47603325425150l
     941: ldc2_w        #527                // long -2258057897108664l
     944: ldc2_w        #529                // long -70349484660027380l
     947: ldc2_w        #531                // long -1507047778731442738l
     950: ldc2_w        #533                // long -4195469843024187482l
     953: ldc2_w        #535                // long -783878768661595604l
     956: ldc2_w        #537                // long -4685085351197651512l
     959: ldc2_w        #539                // long 2615543050766714414l
     962: ldc2_w        #541                // long 6093186943513384366l
     965: ldc2_w        #543                // long 5228386900623932656l
     968: ldc2_w        #545                // long -622594117613578388l
     971: ldc2_w        #547                // long -7503765508084806894l
     974: ldc2_w        #549                // long 6449281599412540682l
     977: ldc2_w        #551                // long 4921942884542611564l
     980: iload_0
     981: iconst_1
     982: isub
     983: dup
     984: istore_0
     985: ifgt          923
     988: ldc           #62                 // int 19
     990: ldc           #23                 // int 33
     992: istore_0
     993: ldc2_w        #553                // long 972l
     996: ldc2_w        #555                // long 204120l
     999: ldc2_w        #557                // long 11234835l
    1002: ldc2_w        #559                // long -960624693l
    1005: ldc2_w        #561                // long -196784350011l
    1008: ldc2_w        #563                // long -15585466550765l
    1011: ldc2_w        #565                // long -768039509530119l
    1014: ldc2_w        #567                // long -26337520900110793l
    1017: ldc2_w        #569                // long -657961025551171999l
    1020: ldc2_w        #571                // long 6217906232626704703l
    1023: ldc2_w        #573                // long -4378916778135944645l
    1026: ldc2_w        #575                // long -6491684318319930271l
    1029: ldc2_w        #577                // long -5279262767991673649l
    1032: ldc2_w        #579                // long 1738109584207253721l
    1035: ldc2_w        #581                // long -6104834775968071709l
    1038: ldc2_w        #583                // long 5332252132885895005l
    1041: ldc2_w        #585                // long -6304913124287651585l
    1044: ldc2_w        #587                // long -6487500512930844483l
    1047: ldc2_w        #589                // long -6037811238840157930l
    1050: iload_0
    1051: iconst_1
    1052: isub
    1053: dup
    1054: istore_0
    1055: ifgt          993
    1058: ldc           #62                 // int 19
    1060: ldc           #23                 // int 33
    1062: istore_0
    1063: ldc2_w        #591                // long 1417176l
    1066: ldc2_w        #593                // long 146677716l
    1069: ldc2_w        #595                // long -4015843758l
    1072: ldc2_w        #597                // long -1539441973665l
    1075: ldc2_w        #599                // long -124726832276310l
    1078: ldc2_w        #601                // long -5804068771740447l
    1081: ldc2_w        #603                // long -182554755923315160l
    1084: ldc2_w        #605                // long -4142426007052871793l
    1087: ldc2_w        #607                // long 3727620600874546078l
    1090: ldc2_w        #609                // long 5952112364986394257l
    1093: ldc2_w        #611                // long 927574149897768728l
    1096: ldc2_w        #613                // long 6079429856602446645l
    1099: ldc2_w        #615                // long -3643130350962660282l
    1102: ldc2_w        #617                // long 2168029387855327547l
    1105: ldc2_w        #619                // long -6463581842772415792l
    1108: ldc2_w        #621                // long 1174929175800435549l
    1111: ldc2_w        #623                // long -470396413515216806l
    1114: ldc2_w        #625                // long -2980173778076805377l
    1117: ldc2_w        #627                // long 942145539884111070l
    1120: iload_0
    1121: iconst_1
    1122: isub
    1123: dup
    1124: istore_0
    1125: ifgt          1063
    1128: ldc           #62                 // int 19
    1130: ldc           #23                 // int 33
    1132: istore_0
    1133: ldc2_w        #629                // long 93312l
    1136: ldc2_w        #631                // long 11959488l
    1139: ldc2_w        #633                // long -134527392l
    1142: ldc2_w        #635                // long -114804549072l
    1145: ldc2_w        #637                // long -9853474506840l
    1148: ldc2_w        #639                // long -452894163515004l
    1151: ldc2_w        #641                // long -13458284062198094l
    1154: ldc2_w        #643                // long -278374520780758679l
    1157: ldc2_w        #645                // long -4162703879366499597l
    1160: ldc2_w        #647                // long -9052774182756655904l
    1163: ldc2_w        #649                // long 9202205934571414400l
    1166: ldc2_w        #651                // long -2326913859693466110l
    1169: ldc2_w        #653                // long -3868574266836531402l
    1172: ldc2_w        #655                // long 746330790610071188l
    1175: ldc2_w        #657                // long 3052976996760480010l
    1178: ldc2_w        #659                // long -4238071449677711139l
    1181: ldc2_w        #661                // long 8240144322000336199l
    1184: ldc2_w        #663                // long -9129665124693863472l
    1187: ldc2_w        #665                // long 5587270281781684940l
    1190: iload_0
    1191: iconst_1
    1192: isub
    1193: dup
    1194: istore_0
    1195: ifgt          1133
    1198: ldc           #62                 // int 19
    1200: ldc           #23                 // int 33
    1202: istore_0
    1203: ldc2_w        #289                // long 5184l
    1206: ldc2_w        #667                // long 605664l
    1209: ldc2_w        #669                // long -14591232l
    1212: ldc2_w        #671                // long -7343029392l
    1215: ldc2_w        #673                // long -677769486812l
    1218: ldc2_w        #675                // long -35749506471754l
    1221: ldc2_w        #677                // long -1274313463151274l
    1224: ldc2_w        #679                // long -32772531088213716l
    1227: ldc2_w        #681                // long -627803448305119896l
    1230: ldc2_w        #683                // long -9099183682080612246l
    1233: ldc2_w        #685                // long -8092041892745764350l
    1236: ldc2_w        #687                // long 9044352735169542936l
    1239: ldc2_w        #689                // long -4592187226848046268l
    1242: ldc2_w        #691                // long 2993434728687034666l
    1245: ldc2_w        #693                // long 5913162569070779930l
    1248: ldc2_w        #695                // long -6153021115901972084l
    1251: ldc2_w        #697                // long 3488133930936942000l
    1254: ldc2_w        #699                // long -2879243489195954538l
    1257: ldc2_w        #701                // long -2214458052120637746l
    1260: iload_0
    1261: iconst_1
    1262: isub
    1263: dup
    1264: istore_0
    1265: ifgt          1203
    1268: ldc           #62                 // int 19
    1270: ldc           #23                 // int 33
    1272: istore_0
    1273: ldc2_w        #703                // long 3456l
    1276: ldc2_w        #705                // long 560448l
    1279: ldc2_w        #707                // long 14224224l
    1282: ldc2_w        #709                // long -3849366064l
    1285: ldc2_w        #711                // long -493941252504l
    1288: ldc2_w        #713                // long -31089264543316l
    1291: ldc2_w        #715                // long -1269181677017390l
    1294: ldc2_w        #717                // long -36644724751179937l
    1297: ldc2_w        #719                // long -777900416972147126l
    1300: ldc2_w        #721                // long 6077914311372410225l
    1303: ldc2_w        #723                // long -773704009072258584l
    1306: ldc2_w        #725                // long 6119395773709755494l
    1309: ldc2_w        #727                // long 6399014073100880476l
    1312: ldc2_w        #729                // long -8237875642048388530l
    1315: ldc2_w        #731                // long 620951651366956354l
    1318: ldc2_w        #733                // long 4270677452932226779l
    1321: ldc2_w        #735                // long 130695344685096210l
    1324: ldc2_w        #737                // long -7848904709743030043l
    1327: ldc2_w        #739                // long -1717748500440447740l
    1330: iload_0
    1331: iconst_1
    1332: isub
    1333: dup
    1334: istore_0
    1335: ifgt          1273
    1338: ldc           #62                 // int 19
    1340: ldc           #23                 // int 33
    1342: istore_0
    1343: ldc2_w        #741                // long 27l
    1346: ldc2_w        #743                // long -549l
    1349: ldc2_w        #745                // long -196302l
    1352: ldc2_w        #747                // long -7406030l
    1355: ldc2_w        #749                // long -102842573l
    1358: ldc2_w        #751                // long -489714573l
    1361: iload_0
    1362: iconst_1
    1363: isub
    1364: dup
    1365: istore_0
    1366: ifgt          1343
    1369: ldc_w         #753                // int 6
    1372: ldc           #23                 // int 33
    1374: istore_0
    1375: ldc2_w        #754                // long 9l
    1378: ldc2_w        #756                // long -801l
    1381: ldc2_w        #758                // long -21865l
    1384: ldc2_w        #760                // long -145391l
    1387: ldc2_w        #762                // long -261744l
    1390: iload_0
    1391: iconst_1
    1392: isub
    1393: dup
    1394: istore_0
    1395: ifgt          1375
    1398: ldc_w         #764                // int 5
    1401: ldc           #23                 // int 33
    1403: istore_0
    1404: ldc2_w        #765                // long 3l
    1407: ldc2_w        #767                // long -235l
    1410: ldc2_w        #769                // long -15631l
    1413: ldc2_w        #771                // long -104673l
    1416: iload_0
    1417: iconst_1
    1418: isub
    1419: dup
    1420: istore_0
    1421: ifgt          1404
    1424: ldc_w         #773                // int 4
    1427: ldc           #23                 // int 33
    1429: istore_0
    1430: ldc2_w        #774                // long 6l
    1433: ldc2_w        #776                // long -455l
    1436: ldc2_w        #778                // long -15113l
    1439: ldc2_w        #780                // long -91902l
    1442: iload_0
    1443: iconst_1
    1444: isub
    1445: dup
    1446: istore_0
    1447: ifgt          1430
    1450: ldc_w         #773                // int 4
    1453: ldc           #23                 // int 33
    1455: istore_0
    1456: ldc2_w        #782                // long 2l
    1459: ldc2_w        #784                // long -53l
    1462: ldc2_w        #786                // long -17165l
    1465: ldc2_w        #788                // long -417484l
    1468: iload_0
    1469: iconst_1
    1470: isub
    1471: dup
    1472: istore_0
    1473: ifgt          1456
    1476: ldc_w         #773                // int 4
    1479: ldc           #23                 // int 33
    1481: istore_0
    1482: ldc2_w        #754                // long 9l
    1485: ldc2_w        #790                // long -609l
    1488: ldc2_w        #792                // long -25745l
    1491: ldc2_w        #794                // long -215127l
    1494: iload_0
    1495: iconst_1
    1496: isub
    1497: dup
    1498: istore_0
    1499: ifgt          1482
    1502: ldc_w         #773                // int 4
    1505: ldc           #23                 // int 33
    1507: istore_0
    1508: ldc2_w        #765                // long 3l
    1511: ldc2_w        #796                // long -307l
    1514: ldc2_w        #798                // long -4251l
    1517: ldc2_w        #800                // long -13685l
    1520: iload_0
    1521: iconst_1
    1522: isub
    1523: dup
    1524: istore_0
    1525: ifgt          1508
    1528: ldc_w         #773                // int 4
    1531: ldc           #23                 // int 33
    1533: istore_0
    1534: ldc2_w        #802                // long 1l
    1537: ldc2_w        #804                // long -58l
    1540: ldc2_w        #806                // long -5825l
    1543: ldc2_w        #808                // long -63726l
    1546: iload_0
    1547: iconst_1
    1548: isub
    1549: dup
    1550: istore_0
    1551: ifgt          1534
    1554: ldc_w         #773                // int 4
    1557: ldc           #23                 // int 33
    1559: istore_0
    1560: ldc2_w        #782                // long 2l
    1563: ldc2_w        #810                // long -191l
    1566: ldc2_w        #812                // long -5031l
    1569: iload_0
    1570: iconst_1
    1571: isub
    1572: dup
    1573: istore_0
    1574: ifgt          1560
    1577: ldc_w         #814                // int 3
    1580: ldc           #23                 // int 33
    1582: istore_0
    1583: ldc2_w        #765                // long 3l
    1586: ldc2_w        #815                // long -290l
    1589: ldc2_w        #817                // long -1313l
    1592: iload_0
    1593: iconst_1
    1594: isub
    1595: dup
    1596: istore_0
    1597: ifgt          1583
    1600: ldc_w         #814                // int 3
    1603: ldc           #23                 // int 33
    1605: istore_0
    1606: ldc2_w        #765                // long 3l
    1609: ldc2_w        #819                // long -346l
    1612: ldc2_w        #821                // long -232l
    1615: iload_0
    1616: iconst_1
    1617: isub
    1618: dup
    1619: istore_0
    1620: ifgt          1606
    1623: ldc_w         #814                // int 3
    1626: ldc           #23                 // int 33
    1628: istore_0
    1629: ldc2_w        #765                // long 3l
    1632: ldc2_w        #821                // long -232l
    1635: ldc2_w        #823                // long -5723l
    1638: iload_0
    1639: iconst_1
    1640: isub
    1641: dup
    1642: istore_0
    1643: ifgt          1629
    1646: ldc_w         #814                // int 3
    1649: ldc           #23                 // int 33
    1651: istore_0
    1652: ldc2_w        #765                // long 3l
    1655: ldc2_w        #825                // long -296l
    1658: ldc2_w        #827                // long -3379l
    1661: iload_0
    1662: iconst_1
    1663: isub
    1664: dup
    1665: istore_0
    1666: ifgt          1652
    1669: ldc_w         #814                // int 3
    1672: ldc           #23                 // int 33
    1674: istore_0
    1675: ldc2_w        #802                // long 1l
    1678: ldc2_w        #829                // long -68l
    1681: ldc2_w        #831                // long -2813l
    1684: iload_0
    1685: iconst_1
    1686: isub
    1687: dup
    1688: istore_0
    1689: ifgt          1675
    1692: ldc_w         #814                // int 3
    1695: ldc_w         #833                // int 95
    1698: istore_0
    1699: istore_2
    1700: iconst_0
    1701: istore_3
    1702: lconst_0
    1703: lstore        4
    1705: iload_3
    1706: ifne          1712
    1709: goto          1765
    1712: iconst_0
    1713: istore        6
    1715: iload_0
    1716: i2l
    1717: iload         6
    1719: iconst_1
    1720: iadd
    1721: dup
    1722: istore        6
    1724: iload_3
    1725: if_icmplt     1715
    1728: iconst_0
    1729: istore        6
    1731: lstore        10
    1733: lstore        8
    1735: lconst_0
    1736: lload         8
    1738: ladd
    1739: lload         10
    1741: lconst_1
    1742: lsub
    1743: dup2
    1744: lstore        10
    1746: lconst_0
    1747: lcmp
    1748: ifne          1736
    1751: iload         6
    1753: iconst_1
    1754: iadd
    1755: dup
    1756: istore        6
    1758: iload_3
    1759: if_icmplt     1731
    1762: goto          1765
    1765: lload         4
    1767: ladd
    1768: lstore        4
    1770: iload_3
    1771: iconst_1
    1772: iadd
    1773: dup
    1774: istore_3
    1775: iload_2
    1776: if_icmplt     1705
    1779: lload         4
    1781: lconst_0
    1782: lcmp
    1783: ifne          1788
    1786: iload_0
    1787: istore_1
    1788: iload_0
    1789: iconst_1
    1790: iadd
    1791: dup
    1792: istore_0
    1793: ldc_w         #834                // int 128
    1796: if_icmplt     1700
    1799: getstatic     #13                 // Field java/lang/System.out:Ljava/io/PrintStream;
    1802: iload_1
    1803: i2c
    1804: invokevirtual #837                // Method java/io/PrintStream.print:(C)V
    1807: dup
    1808: ifne          1695
    1811: return
}
