.version 49 0
.class public Main
.super java/lang/Object

.method public static main : ([Ljava/lang/String;)V
    .code stack 865 locals 12
L0:     getstatic Field java/lang/System out Ljava/io/PrintStream;
L3:     ldc "\u000A\u000A==================================================\u000Awelcome to the bear flag calculator!\u000Acalculating your flag... please be patient...\u000Ayour flag is: "
L5:     invokevirtual Method java/io/PrintStream print (Ljava/lang/String;)V
L8:     ldc 0
L10:    ldc 33
L12:    istore_0
L13:    ldc2_w 139968L
L16:    ldc2_w 5668704L
L19:    ldc2_w -1304525088L
L22:    ldc2_w -136713343536L
L25:    ldc2_w -6199669846548L
L28:    ldc2_w -168942465814554L
L31:    ldc2_w -3090696072809988L
L34:    ldc2_w -40091725176298332L
L37:    ldc2_w -380192091498886956L
L40:    ldc2_w -2681484757726506270L
L43:    ldc2_w 4262732026354931284L
L46:    ldc2_w -1010288408357244504L
L49:    ldc2_w -1290340284545482380L
L52:    ldc2_w 2078316189846199370L
L55:    ldc2_w 8600033438064957380L
L58:    ldc2_w 1420642205836072100L
L61:    ldc2_w -8455265360534582900L
L64:    ldc2_w 1665170620416952526L
L67:    ldc2_w -1301775785128209268L
L70:    iload_0
L71:    iconst_1
L72:    isub
L73:    dup
L74:    istore_0
L75:    ifgt L13
L78:    ldc 19
L80:    ldc 33
L82:    istore_0
L83:    ldc2_w 8748L
L86:    ldc2_w 1414260L
L89:    ldc2_w 26723439L
L92:    ldc2_w -10660294170L
L95:    ldc2_w -1221377280201L
L98:    ldc2_w -69067032564330L
L101:   ldc2_w -2484601406995677L
L104:   ldc2_w -61766129802830370L
L107:   ldc2_w -1102152172282805925L
L110:   ldc2_w 4064385248137766326L
L113:   ldc2_w -9180640905693487451L
L116:   ldc2_w -2428929420931013902L
L119:   ldc2_w 7433817110216891877L
L122:   ldc2_w 570301496243907042L
L125:   ldc2_w 5254839426900975617L
L128:   ldc2_w -1280151659966208822L
L131:   ldc2_w -8888534056241547107L
L134:   ldc2_w 3270166363338602206L
L137:   ldc2_w -7827650834523256696L
L140:   iload_0
L141:   iconst_1
L142:   isub
L143:   dup
L144:   istore_0
L145:   ifgt L83
L148:   ldc 19
L150:   ldc 33
L152:   istore_0
L153:   ldc2_w 576L
L156:   ldc2_w 146496L
L159:   ldc2_w 12112048L
L162:   ldc2_w -275935968L
L165:   ldc2_w -147400189732L
L168:   ldc2_w -15435698167996L
L171:   ldc2_w -963396145601043L
L174:   ldc2_w -41855620854074132L
L177:   ldc2_w -1341408083771387994L
L180:   ldc2_w 4312977838210654592L
L183:   ldc2_w 1791641609139274227L
L186:   ldc2_w -3503117117902889960L
L189:   ldc2_w -3088454007629645152L
L192:   ldc2_w 8848217138088398820L
L195:   ldc2_w 3062279033678910147L
L198:   ldc2_w -6684007589624798244L
L201:   ldc2_w 4740777470248945982L
L204:   ldc2_w 9040021092677972248L
L207:   ldc2_w 3652210279687931405L
L210:   iload_0
L211:   iconst_1
L212:   isub
L213:   dup
L214:   istore_0
L215:   ifgt L153
L218:   ldc 19
L220:   ldc 33
L222:   istore_0
L223:   ldc2_w 46656L
L226:   ldc2_w 6788448L
L229:   ldc2_w 39481344L
L232:   ldc2_w -58856964336L
L235:   ldc2_w -6103475822700L
L238:   ldc2_w -332663882200458L
L241:   ldc2_w -11846817654688062L
L244:   ldc2_w -297391697652357612L
L247:   ldc2_w -5448907467944869656L
L250:   ldc2_w -240756732184936670L
L253:   ldc2_w 7557340208061021758L
L256:   ldc2_w -3055365093473528504L
L259:   ldc2_w 862558048250048660L
L262:   ldc2_w 8515228054694805722L
L265:   ldc2_w -7642578819372557762L
L268:   ldc2_w -3454788906313965484L
L271:   ldc2_w -4477929424018395536L
L274:   ldc2_w 2988288913377215854L
L277:   ldc2_w -4830491881878959358L
L280:   iload_0
L281:   iconst_1
L282:   isub
L283:   dup
L284:   istore_0
L285:   ifgt L223
L288:   ldc 19
L290:   ldc 33
L292:   istore_0
L293:   ldc2_w 34992L
L296:   ldc2_w 5015520L
L299:   ldc2_w 102054168L
L302:   ldc2_w -29631948768L
L305:   ldc2_w -3372424301925L
L308:   ldc2_w -192396619525590L
L311:   ldc2_w -7195231516974519L
L314:   ldc2_w -192191118265946044L
L317:   ldc2_w -3814454414305521069L
L320:   ldc2_w -2039952563681889898L
L323:   ldc2_w 4210575270153678009L
L326:   ldc2_w 6197086543140623960L
L329:   ldc2_w -8480945980504676871L
L332:   ldc2_w -2409180279491630794L
L335:   ldc2_w -2611622199478744541L
L338:   ldc2_w -4246470620712608252L
L341:   ldc2_w 1457600041085969513L
L344:   ldc2_w 727591600248688234L
L347:   ldc2_w 4873507416256484803L
L350:   iload_0
L351:   iconst_1
L352:   isub
L353:   dup
L354:   istore_0
L355:   ifgt L293
L358:   ldc 19
L360:   ldc 33
L362:   istore_0
L363:   ldc2_w 34992L
L366:   ldc2_w 2437776L
L369:   ldc2_w -136554336L
L372:   ldc2_w -22142284740L
L375:   ldc2_w -1155643517547L
L378:   ldc2_w -34440854121072L
L381:   ldc2_w -671061906273642L
L384:   ldc2_w -9077406493695852L
L387:   ldc2_w -88058569837809285L
L390:   ldc2_w -623934430871284104L
L393:   ldc2_w -3258622023335906448L
L396:   ldc2_w 5876162155016540260L
L399:   ldc2_w 1231306228709245595L
L402:   ldc2_w 222499297403274784L
L405:   ldc2_w 2569385785572497022L
L408:   ldc2_w 1310833369215277644L
L411:   ldc2_w 2010343674646223941L
L414:   ldc2_w -8821384138009525304L
L417:   ldc2_w -4508618494801320900L
L420:   iload_0
L421:   iconst_1
L422:   isub
L423:   dup
L424:   istore_0
L425:   ifgt L363
L428:   ldc 19
L430:   ldc 33
L432:   istore_0
L433:   ldc2_w 1679616L
L436:   ldc2_w 277136640L
L439:   ldc2_w 9692970624L
L442:   ldc2_w -1422224101440L
L445:   ldc2_w -204338969339904L
L448:   ldc2_w -13478104966543920L
L451:   ldc2_w -574707629113712856L
L454:   ldc2_w 1007863641486612436L
L457:   ldc2_w -5197709306964673473L
L460:   ldc2_w -8387002613302458838L
L463:   ldc2_w -8206330036474289953L
L466:   ldc2_w 4013747348815460624L
L469:   ldc2_w 3274496121279401134L
L472:   ldc2_w -5313291341872763108L
L475:   ldc2_w 3620609337395217774L
L478:   ldc2_w -9025275002787940948L
L481:   ldc2_w -1220755215152531853L
L484:   ldc2_w -4109684211436336742L
L487:   ldc2_w 4924223426003895211L
L490:   iload_0
L491:   iconst_1
L492:   isub
L493:   dup
L494:   istore_0
L495:   ifgt L433
L498:   ldc 19
L500:   ldc 33
L502:   istore_0
L503:   ldc2_w 5184L
L506:   ldc2_w 884736L
L509:   ldc2_w 23056272L
L512:   ldc2_w -6824846400L
L515:   ldc2_w -914899457860L
L518:   ldc2_w -60350940043552L
L521:   ldc2_w -2583666692190413L
L524:   ldc2_w -78260436991300276L
L527:   ldc2_w -1743625496459165555L
L530:   ldc2_w 7787189488059442192L
L533:   ldc2_w 2477390998100830586L
L536:   ldc2_w -4650455043496741848L
L539:   ldc2_w -8303729601757835578L
L542:   ldc2_w 7484218889437802576L
L545:   ldc2_w 2936373258989651239L
L548:   ldc2_w 3169085310323819692L
L551:   ldc2_w 1300550019928774049L
L554:   ldc2_w 386990088051114720L
L557:   ldc2_w -8896528384153874260L
L560:   iload_0
L561:   iconst_1
L562:   isub
L563:   dup
L564:   istore_0
L565:   ifgt L503
L568:   ldc 19
L570:   ldc 33
L572:   istore_0
L573:   ldc2_w 104976L
L576:   ldc2_w 25876584L
L579:   ldc2_w 2207064996L
L582:   ldc2_w -1421067402L
L585:   ldc2_w -16975173429054L
L588:   ldc2_w -1787546503915218L
L591:   ldc2_w -107028057723819894L
L594:   ldc2_w -4405879701728549154L
L597:   ldc2_w -4038252538400293702L
L600:   ldc2_w -921567798844201370L
L603:   ldc2_w 3047470220774532874L
L606:   ldc2_w 1443679329959270978L
L609:   ldc2_w -727597003368712666L
L612:   ldc2_w 4788714558851661930L
L615:   ldc2_w -181319753990644770L
L618:   ldc2_w 3270964186097359338L
L621:   ldc2_w 3404651935777878478L
L624:   ldc2_w -6769392680452861670L
L627:   ldc2_w -3993177484119107222L
L630:   iload_0
L631:   iconst_1
L632:   isub
L633:   dup
L634:   istore_0
L635:   ifgt L573
L638:   ldc 19
L640:   ldc 33
L642:   istore_0
L643:   ldc2_w 10368L
L646:   ldc2_w 2401920L
L649:   ldc2_w 183307104L
L652:   ldc2_w -2406889536L
L655:   ldc2_w -1548736359688L
L658:   ldc2_w -142728231469336L
L661:   ldc2_w -7618121483991942L
L664:   ldc2_w -277207393691124592L
L667:   ldc2_w -7286275161642921244L
L670:   ldc2_w 5728269050213558216L
L673:   ldc2_w 2163257914477573294L
L676:   ldc2_w -1651253694791623968L
L679:   ldc2_w -5332672475574895888L
L682:   ldc2_w 5670581969580992184L
L685:   ldc2_w 4722922663732830262L
L688:   ldc2_w -5140488267151724464L
L691:   ldc2_w 2857217307181004404L
L694:   ldc2_w 3689631063985650840L
L697:   ldc2_w -7544184654336337022L
L700:   iload_0
L701:   iconst_1
L702:   isub
L703:   dup
L704:   istore_0
L705:   ifgt L643
L708:   ldc 19
L710:   ldc 33
L712:   istore_0
L713:   ldc2_w 46656L
L716:   ldc2_w 4385664L
L719:   ldc2_w -201003120L
L722:   ldc2_w -53814639168L
L725:   ldc2_w -4013457016212L
L728:   ldc2_w -173617432839240L
L731:   ldc2_w -5042862562373013L
L734:   ldc2_w -104488640651251224L
L737:   ldc2_w -1591746789722905338L
L740:   ldc2_w 354495864531750664L
L743:   ldc2_w -6599072343152943871L
L746:   ldc2_w -4411242035675151760L
L749:   ldc2_w 40341593311307744L
L752:   ldc2_w 5319299384879524584L
L755:   ldc2_w 2112449841113457213L
L758:   ldc2_w 361235905345368744L
L761:   ldc2_w 4874699891546192526L
L764:   ldc2_w -6481032793851284968L
L767:   ldc2_w -3793531303538899289L
L770:   iload_0
L771:   iconst_1
L772:   isub
L773:   dup
L774:   istore_0
L775:   ifgt L713
L778:   ldc 19
L780:   ldc 33
L782:   istore_0
L783:   ldc2_w 15552L
L786:   ldc2_w 4183488L
L789:   ldc2_w 373073904L
L792:   ldc2_w -4329354672L
L795:   ldc2_w -3953354662764L
L798:   ldc2_w -422427961750700L
L801:   ldc2_w -26010393342733715L
L804:   ldc2_w -1093860902509714309L
L807:   ldc2_w 3490423937368633287L
L810:   ldc2_w -5464188247457000747L
L813:   ldc2_w -3681525459521522362L
L816:   ldc2_w 5370563176357251742L
L819:   ldc2_w -800638681479098462L
L822:   ldc2_w 4585505281331689694L
L825:   ldc2_w 706712822569378793L
L828:   ldc2_w -7236641882254413177L
L831:   ldc2_w 2632951496217652339L
L834:   ldc2_w -3704181124037433527L
L837:   ldc2_w 825596779461060420L
L840:   iload_0
L841:   iconst_1
L842:   isub
L843:   dup
L844:   istore_0
L845:   ifgt L783
L848:   ldc 19
L850:   ldc 33
L852:   istore_0
L853:   ldc2_w 78732L
L856:   ldc2_w 6928416L
L859:   ldc2_w -227358333L
L862:   ldc2_w -58603762521L
L865:   ldc2_w -3712208766255L
L868:   ldc2_w -132333403855653L
L871:   ldc2_w -3102068925468351L
L874:   ldc2_w -51060111466457637L
L877:   ldc2_w -610981839411598827L
L880:   ldc2_w -5419154092790447537L
L883:   ldc2_w 909882275855010683L
L886:   ldc2_w 5100093266219088197L
L889:   ldc2_w -4593515856727495933L
L892:   ldc2_w 376691970646840769L
L895:   ldc2_w -246464679650945717L
L898:   ldc2_w 5733858527181028217L
L901:   ldc2_w 3120592970343724235L
L904:   ldc2_w 7401133743249552309L
L907:   ldc2_w -6503471003769017290L
L910:   iload_0
L911:   iconst_1
L912:   isub
L913:   dup
L914:   istore_0
L915:   ifgt L853
L918:   ldc 19
L920:   ldc 33
L922:   istore_0
L923:   ldc2_w 2592L
L926:   ldc2_w 629856L
L929:   ldc2_w 44302320L
L932:   ldc2_w -2073761280L
L935:   ldc2_w -581570685934L
L938:   ldc2_w -47603325425150L
L941:   ldc2_w -2258057897108664L
L944:   ldc2_w -70349484660027380L
L947:   ldc2_w -1507047778731442738L
L950:   ldc2_w -4195469843024187482L
L953:   ldc2_w -783878768661595604L
L956:   ldc2_w -4685085351197651512L
L959:   ldc2_w 2615543050766714414L
L962:   ldc2_w 6093186943513384366L
L965:   ldc2_w 5228386900623932656L
L968:   ldc2_w -622594117613578388L
L971:   ldc2_w -7503765508084806894L
L974:   ldc2_w 6449281599412540682L
L977:   ldc2_w 4921942884542611564L
L980:   iload_0
L981:   iconst_1
L982:   isub
L983:   dup
L984:   istore_0
L985:   ifgt L923
L988:   ldc 19
L990:   ldc 33
L992:   istore_0
L993:   ldc2_w 972L
L996:   ldc2_w 204120L
L999:   ldc2_w 11234835L
L1002:  ldc2_w -960624693L
L1005:  ldc2_w -196784350011L
L1008:  ldc2_w -15585466550765L
L1011:  ldc2_w -768039509530119L
L1014:  ldc2_w -26337520900110793L
L1017:  ldc2_w -657961025551171999L
L1020:  ldc2_w 6217906232626704703L
L1023:  ldc2_w -4378916778135944645L
L1026:  ldc2_w -6491684318319930271L
L1029:  ldc2_w -5279262767991673649L
L1032:  ldc2_w 1738109584207253721L
L1035:  ldc2_w -6104834775968071709L
L1038:  ldc2_w 5332252132885895005L
L1041:  ldc2_w -6304913124287651585L
L1044:  ldc2_w -6487500512930844483L
L1047:  ldc2_w -6037811238840157930L
L1050:  iload_0
L1051:  iconst_1
L1052:  isub
L1053:  dup
L1054:  istore_0
L1055:  ifgt L993
L1058:  ldc 19
L1060:  ldc 33
L1062:  istore_0
L1063:  ldc2_w 1417176L
L1066:  ldc2_w 146677716L
L1069:  ldc2_w -4015843758L
L1072:  ldc2_w -1539441973665L
L1075:  ldc2_w -124726832276310L
L1078:  ldc2_w -5804068771740447L
L1081:  ldc2_w -182554755923315160L
L1084:  ldc2_w -4142426007052871793L
L1087:  ldc2_w 3727620600874546078L
L1090:  ldc2_w 5952112364986394257L
L1093:  ldc2_w 927574149897768728L
L1096:  ldc2_w 6079429856602446645L
L1099:  ldc2_w -3643130350962660282L
L1102:  ldc2_w 2168029387855327547L
L1105:  ldc2_w -6463581842772415792L
L1108:  ldc2_w 1174929175800435549L
L1111:  ldc2_w -470396413515216806L
L1114:  ldc2_w -2980173778076805377L
L1117:  ldc2_w 942145539884111070L
L1120:  iload_0
L1121:  iconst_1
L1122:  isub
L1123:  dup
L1124:  istore_0
L1125:  ifgt L1063
L1128:  ldc 19
L1130:  ldc 33
L1132:  istore_0
L1133:  ldc2_w 93312L
L1136:  ldc2_w 11959488L
L1139:  ldc2_w -134527392L
L1142:  ldc2_w -114804549072L
L1145:  ldc2_w -9853474506840L
L1148:  ldc2_w -452894163515004L
L1151:  ldc2_w -13458284062198094L
L1154:  ldc2_w -278374520780758679L
L1157:  ldc2_w -4162703879366499597L
L1160:  ldc2_w -9052774182756655904L
L1163:  ldc2_w 9202205934571414400L
L1166:  ldc2_w -2326913859693466110L
L1169:  ldc2_w -3868574266836531402L
L1172:  ldc2_w 746330790610071188L
L1175:  ldc2_w 3052976996760480010L
L1178:  ldc2_w -4238071449677711139L
L1181:  ldc2_w 8240144322000336199L
L1184:  ldc2_w -9129665124693863472L
L1187:  ldc2_w 5587270281781684940L
L1190:  iload_0
L1191:  iconst_1
L1192:  isub
L1193:  dup
L1194:  istore_0
L1195:  ifgt L1133
L1198:  ldc 19
L1200:  ldc 33
L1202:  istore_0
L1203:  ldc2_w 5184L
L1206:  ldc2_w 605664L
L1209:  ldc2_w -14591232L
L1212:  ldc2_w -7343029392L
L1215:  ldc2_w -677769486812L
L1218:  ldc2_w -35749506471754L
L1221:  ldc2_w -1274313463151274L
L1224:  ldc2_w -32772531088213716L
L1227:  ldc2_w -627803448305119896L
L1230:  ldc2_w -9099183682080612246L
L1233:  ldc2_w -8092041892745764350L
L1236:  ldc2_w 9044352735169542936L
L1239:  ldc2_w -4592187226848046268L
L1242:  ldc2_w 2993434728687034666L
L1245:  ldc2_w 5913162569070779930L
L1248:  ldc2_w -6153021115901972084L
L1251:  ldc2_w 3488133930936942000L
L1254:  ldc2_w -2879243489195954538L
L1257:  ldc2_w -2214458052120637746L
L1260:  iload_0
L1261:  iconst_1
L1262:  isub
L1263:  dup
L1264:  istore_0
L1265:  ifgt L1203
L1268:  ldc 19
L1270:  ldc 33
L1272:  istore_0
L1273:  ldc2_w 3456L
L1276:  ldc2_w 560448L
L1279:  ldc2_w 14224224L
L1282:  ldc2_w -3849366064L
L1285:  ldc2_w -493941252504L
L1288:  ldc2_w -31089264543316L
L1291:  ldc2_w -1269181677017390L
L1294:  ldc2_w -36644724751179937L
L1297:  ldc2_w -777900416972147126L
L1300:  ldc2_w 6077914311372410225L
L1303:  ldc2_w -773704009072258584L
L1306:  ldc2_w 6119395773709755494L
L1309:  ldc2_w 6399014073100880476L
L1312:  ldc2_w -8237875642048388530L
L1315:  ldc2_w 620951651366956354L
L1318:  ldc2_w 4270677452932226779L
L1321:  ldc2_w 130695344685096210L
L1324:  ldc2_w -7848904709743030043L
L1327:  ldc2_w -1717748500440447740L
L1330:  iload_0
L1331:  iconst_1
L1332:  isub
L1333:  dup
L1334:  istore_0
L1335:  ifgt L1273
L1338:  ldc 19
L1340:  ldc 33
L1342:  istore_0
L1343:  ldc2_w 27L
L1346:  ldc2_w -549L
L1349:  ldc2_w -196302L
L1352:  ldc2_w -7406030L
L1355:  ldc2_w -102842573L
L1358:  ldc2_w -489714573L
L1361:  iload_0
L1362:  iconst_1
L1363:  isub
L1364:  dup
L1365:  istore_0
L1366:  ifgt L1343
L1369:  ldc_w 6
L1372:  ldc 33
L1374:  istore_0
L1375:  ldc2_w 9L
L1378:  ldc2_w -801L
L1381:  ldc2_w -21865L
L1384:  ldc2_w -145391L
L1387:  ldc2_w -261744L
L1390:  iload_0
L1391:  iconst_1
L1392:  isub
L1393:  dup
L1394:  istore_0
L1395:  ifgt L1375
L1398:  ldc_w 5
L1401:  ldc 33
L1403:  istore_0
L1404:  ldc2_w 3L
L1407:  ldc2_w -235L
L1410:  ldc2_w -15631L
L1413:  ldc2_w -104673L
L1416:  iload_0
L1417:  iconst_1
L1418:  isub
L1419:  dup
L1420:  istore_0
L1421:  ifgt L1404
L1424:  ldc_w 4
L1427:  ldc 33
L1429:  istore_0
L1430:  ldc2_w 6L
L1433:  ldc2_w -455L
L1436:  ldc2_w -15113L
L1439:  ldc2_w -91902L
L1442:  iload_0
L1443:  iconst_1
L1444:  isub
L1445:  dup
L1446:  istore_0
L1447:  ifgt L1430
L1450:  ldc_w 4
L1453:  ldc 33
L1455:  istore_0
L1456:  ldc2_w 2L
L1459:  ldc2_w -53L
L1462:  ldc2_w -17165L
L1465:  ldc2_w -417484L
L1468:  iload_0
L1469:  iconst_1
L1470:  isub
L1471:  dup
L1472:  istore_0
L1473:  ifgt L1456
L1476:  ldc_w 4
L1479:  ldc 33
L1481:  istore_0
L1482:  ldc2_w 9L
L1485:  ldc2_w -609L
L1488:  ldc2_w -25745L
L1491:  ldc2_w -215127L
L1494:  iload_0
L1495:  iconst_1
L1496:  isub
L1497:  dup
L1498:  istore_0
L1499:  ifgt L1482
L1502:  ldc_w 4
L1505:  ldc 33
L1507:  istore_0
L1508:  ldc2_w 3L
L1511:  ldc2_w -307L
L1514:  ldc2_w -4251L
L1517:  ldc2_w -13685L
L1520:  iload_0
L1521:  iconst_1
L1522:  isub
L1523:  dup
L1524:  istore_0
L1525:  ifgt L1508
L1528:  ldc_w 4
L1531:  ldc 33
L1533:  istore_0
L1534:  ldc2_w 1L
L1537:  ldc2_w -58L
L1540:  ldc2_w -5825L
L1543:  ldc2_w -63726L
L1546:  iload_0
L1547:  iconst_1
L1548:  isub
L1549:  dup
L1550:  istore_0
L1551:  ifgt L1534
L1554:  ldc_w 4
L1557:  ldc 33
L1559:  istore_0
L1560:  ldc2_w 2L
L1563:  ldc2_w -191L
L1566:  ldc2_w -5031L
L1569:  iload_0
L1570:  iconst_1
L1571:  isub
L1572:  dup
L1573:  istore_0
L1574:  ifgt L1560
L1577:  ldc_w 3
L1580:  ldc 33
L1582:  istore_0
L1583:  ldc2_w 3L
L1586:  ldc2_w -290L
L1589:  ldc2_w -1313L
L1592:  iload_0
L1593:  iconst_1
L1594:  isub
L1595:  dup
L1596:  istore_0
L1597:  ifgt L1583
L1600:  ldc_w 3
L1603:  ldc 33
L1605:  istore_0
L1606:  ldc2_w 3L
L1609:  ldc2_w -346L
L1612:  ldc2_w -232L
L1615:  iload_0
L1616:  iconst_1
L1617:  isub
L1618:  dup
L1619:  istore_0
L1620:  ifgt L1606
L1623:  ldc_w 3
L1626:  ldc 33
L1628:  istore_0
L1629:  ldc2_w 3L
L1632:  ldc2_w -232L
L1635:  ldc2_w -5723L
L1638:  iload_0
L1639:  iconst_1
L1640:  isub
L1641:  dup
L1642:  istore_0
L1643:  ifgt L1629
L1646:  ldc_w 3
L1649:  ldc 33
L1651:  istore_0
L1652:  ldc2_w 3L
L1655:  ldc2_w -296L
L1658:  ldc2_w -3379L
L1661:  iload_0
L1662:  iconst_1
L1663:  isub
L1664:  dup
L1665:  istore_0
L1666:  ifgt L1652
L1669:  ldc_w 3
L1672:  ldc 33
L1674:  istore_0
L1675:  ldc2_w 1L
L1678:  ldc2_w -68L
L1681:  ldc2_w -2813L
L1684:  iload_0
L1685:  iconst_1
L1686:  isub
L1687:  dup
L1688:  istore_0
L1689:  ifgt L1675
L1692:  ldc_w 3
L1695:  ldc_w 95
L1698:  istore_0
L1699:  istore_2
L1700:  iconst_0
L1701:  istore_3
L1702:  lconst_0
L1703:  lstore 4
L1705:  iload_3
L1706:  ifne L1712
L1709:  goto L1765
L1712:  iconst_0
L1713:  istore 6
L1715:  iload_0
L1716:  i2l
L1717:  iload 6
L1719:  iconst_1
L1720:  iadd
L1721:  dup
L1722:  istore 6
L1724:  iload_3
L1725:  if_icmplt L1715
L1728:  iconst_0
L1729:  istore 6
L1731:  lstore 10
L1733:  lstore 8
L1735:  lconst_0
L1736:  lload 8
L1738:  ladd
L1739:  lload 10
L1741:  lconst_1
L1742:  lsub
L1743:  dup2
L1744:  lstore 10
L1746:  lconst_0
L1747:  lcmp
L1748:  ifne L1736
L1751:  iload 6
L1753:  iconst_1
L1754:  iadd
L1755:  dup
L1756:  istore 6
L1758:  iload_3
L1759:  if_icmplt L1731
L1762:  goto L1765
L1765:  lload 4
L1767:  ladd
L1768:  lstore 4
L1770:  iload_3
L1771:  iconst_1
L1772:  iadd
L1773:  dup
L1774:  istore_3
L1775:  iload_2
L1776:  if_icmplt L1705
L1779:  lload 4
L1781:  lconst_0
L1782:  lcmp
L1783:  ifne L1788
L1786:  iload_0
L1787:  istore_1
L1788:  iload_0
L1789:  iconst_1
L1790:  iadd
L1791:  dup
L1792:  istore_0
L1793:  ldc_w 128
L1796:  if_icmplt L1700
L1799:  getstatic Field java/lang/System out Ljava/io/PrintStream;
L1802:  iload_1
L1803:  i2c
L1804:  invokevirtual Method java/io/PrintStream print (C)V
L1807:  dup
L1808:  ifne L1695
L1811:  return
L1812:  
    .end code
.end method
.sourcefile "Main.jasm"
.sourcedebugextension b''
.end class
